{
"meta":{"test_sets":[],"test_metrics":[],"learn_metrics":[{"best_value":"Min","name":"RMSE"}],"launch_mode":"Train","parameters":"","iteration_count":1000,"learn_sets":["learn"],"name":"experiment"},
"iterations":[
{"learn":[206130.845],"iteration":0,"passed_time":0.004533456392,"remaining_time":4.528922935},
{"learn":[192939.8883],"iteration":1,"passed_time":0.008153908221,"remaining_time":4.068800202},
{"learn":[180735.4096],"iteration":2,"passed_time":0.01354861702,"remaining_time":4.502657056},
{"learn":[170319.5628],"iteration":3,"passed_time":0.01737617811,"remaining_time":4.32666835},
{"learn":[161935.5784],"iteration":4,"passed_time":0.02082971092,"remaining_time":4.145112473},
{"learn":[153753.4934],"iteration":5,"passed_time":0.0251729665,"remaining_time":4.17032145},
{"learn":[146924.9156],"iteration":6,"passed_time":0.02902260657,"remaining_time":4.117064046},
{"learn":[140339.0411],"iteration":7,"passed_time":0.03305874757,"remaining_time":4.099284699},
{"learn":[134339.7802],"iteration":8,"passed_time":0.03692661919,"remaining_time":4.066031069},
{"learn":[129274.8363],"iteration":9,"passed_time":0.03996032592,"remaining_time":3.956072266},
{"learn":[124888.348],"iteration":10,"passed_time":0.04379892771,"remaining_time":3.937921773},
{"learn":[120809.0889],"iteration":11,"passed_time":0.04756722382,"remaining_time":3.916368095},
{"learn":[117485.3698],"iteration":12,"passed_time":0.05188648955,"remaining_time":3.939381937},
{"learn":[114376.4808],"iteration":13,"passed_time":0.05604368402,"remaining_time":3.947076603},
{"learn":[111544.4702],"iteration":14,"passed_time":0.0598309426,"remaining_time":3.928898564},
{"learn":[109085.5455],"iteration":15,"passed_time":0.06306884777,"remaining_time":3.878734138},
{"learn":[106809.3853],"iteration":16,"passed_time":0.06627570373,"remaining_time":3.832295104},
{"learn":[104788.6123],"iteration":17,"passed_time":0.07054933284,"remaining_time":3.848858047},
{"learn":[102933.0323],"iteration":18,"passed_time":0.07502940204,"remaining_time":3.873886495},
{"learn":[101497.3789],"iteration":19,"passed_time":0.07936830621,"remaining_time":3.889047005},
{"learn":[99928.30516],"iteration":20,"passed_time":0.08275613415,"remaining_time":3.858012159},
{"learn":[98744.08413],"iteration":21,"passed_time":0.0851332055,"remaining_time":3.784557953},
{"learn":[97650.44939],"iteration":22,"passed_time":0.08888239722,"remaining_time":3.775569656},
{"learn":[96456.72236],"iteration":23,"passed_time":0.09298530719,"remaining_time":3.781402492},
{"learn":[95551.86147],"iteration":24,"passed_time":0.09657596916,"remaining_time":3.766462797},
{"learn":[94716.46972],"iteration":25,"passed_time":0.1151618428,"remaining_time":4.314139802},
{"learn":[93814.99099],"iteration":26,"passed_time":0.1200841678,"remaining_time":4.327477604},
{"learn":[92966.70944],"iteration":27,"passed_time":0.12531808,"remaining_time":4.350327633},
{"learn":[92146.75493],"iteration":28,"passed_time":0.1311716925,"remaining_time":4.391990117},
{"learn":[91335.42774],"iteration":29,"passed_time":0.1361282033,"remaining_time":4.401478574},
{"learn":[90606.79804],"iteration":30,"passed_time":0.1405012556,"remaining_time":4.391797311},
{"learn":[89876.22637],"iteration":31,"passed_time":0.1447769335,"remaining_time":4.379502238},
{"learn":[89399.14466],"iteration":32,"passed_time":0.1484892251,"remaining_time":4.351184262},
{"learn":[88875.50057],"iteration":33,"passed_time":0.1526684436,"remaining_time":4.337579897},
{"learn":[88171.218],"iteration":34,"passed_time":0.1579384756,"remaining_time":4.354589399},
{"learn":[87644.09533],"iteration":35,"passed_time":0.1621312303,"remaining_time":4.341514055},
{"learn":[87270.40229],"iteration":36,"passed_time":0.1670946036,"remaining_time":4.348975764},
{"learn":[86899.24237],"iteration":37,"passed_time":0.1722713381,"remaining_time":4.361184927},
{"learn":[86477.10016],"iteration":38,"passed_time":0.1770290564,"remaining_time":4.362177517},
{"learn":[85985.03467],"iteration":39,"passed_time":0.1817646203,"remaining_time":4.362350887},
{"learn":[85649.09004],"iteration":40,"passed_time":0.1874605911,"remaining_time":4.384748948},
{"learn":[85266.76454],"iteration":41,"passed_time":0.1920021377,"remaining_time":4.379477331},
{"learn":[84922.92593],"iteration":42,"passed_time":0.1956872231,"remaining_time":4.35517843},
{"learn":[84646.70722],"iteration":43,"passed_time":0.19940419,"remaining_time":4.33250922},
{"learn":[84293.53051],"iteration":44,"passed_time":0.2039567508,"remaining_time":4.32841549},
{"learn":[83914.68229],"iteration":45,"passed_time":0.2078853681,"remaining_time":4.311361764},
{"learn":[83515.00835],"iteration":46,"passed_time":0.2137119163,"remaining_time":4.333350133},
{"learn":[83315.47532],"iteration":47,"passed_time":0.218452743,"remaining_time":4.33264607},
{"learn":[83116.63936],"iteration":48,"passed_time":0.223330332,"remaining_time":4.334431545},
{"learn":[82865.69663],"iteration":49,"passed_time":0.2279257765,"remaining_time":4.330589754},
{"learn":[82726.06533],"iteration":50,"passed_time":0.2330473468,"remaining_time":4.336508473},
{"learn":[82555.92519],"iteration":51,"passed_time":0.2375257261,"remaining_time":4.330276698},
{"learn":[82304.96003],"iteration":52,"passed_time":0.2414066066,"remaining_time":4.313435027},
{"learn":[81992.51539],"iteration":53,"passed_time":0.245717202,"remaining_time":4.304601353},
{"learn":[81801.80147],"iteration":54,"passed_time":0.2499962045,"remaining_time":4.295389332},
{"learn":[81630.14721],"iteration":55,"passed_time":0.2544181237,"remaining_time":4.288762657},
{"learn":[81364.8137],"iteration":56,"passed_time":0.2576730977,"remaining_time":4.262907564},
{"learn":[81069.24449],"iteration":57,"passed_time":0.2607693892,"remaining_time":4.235254563},
{"learn":[80806.33723],"iteration":58,"passed_time":0.2646501495,"remaining_time":4.220945604},
{"learn":[80600.85525],"iteration":59,"passed_time":0.268452066,"remaining_time":4.205749034},
{"learn":[80463.88859],"iteration":60,"passed_time":0.2725083122,"remaining_time":4.194841068},
{"learn":[80322.76706],"iteration":61,"passed_time":0.2767801471,"remaining_time":4.187415773},
{"learn":[80044.4687],"iteration":62,"passed_time":0.2809857563,"remaining_time":4.179105613},
{"learn":[79813.77899],"iteration":63,"passed_time":0.2850033069,"remaining_time":4.168173363},
{"learn":[79682.52909],"iteration":64,"passed_time":0.2889763984,"remaining_time":4.156814347},
{"learn":[79574.17849],"iteration":65,"passed_time":0.2930811082,"remaining_time":4.147541744},
{"learn":[79342.58695],"iteration":66,"passed_time":0.310905353,"remaining_time":4.32947305},
{"learn":[79219.99076],"iteration":67,"passed_time":0.3169575649,"remaining_time":4.344183095},
{"learn":[79114.90661],"iteration":68,"passed_time":0.3234612229,"remaining_time":4.364382587},
{"learn":[79063.12433],"iteration":69,"passed_time":0.3290599533,"remaining_time":4.371796523},
{"learn":[78878.19169],"iteration":70,"passed_time":0.3355419269,"remaining_time":4.390400706},
{"learn":[78801.83981],"iteration":71,"passed_time":0.3531583279,"remaining_time":4.551818449},
{"learn":[78513.34533],"iteration":72,"passed_time":0.3583218342,"remaining_time":4.550196442},
{"learn":[78431.8928],"iteration":73,"passed_time":0.3645706619,"remaining_time":4.562059904},
{"learn":[78337.82397],"iteration":74,"passed_time":0.3717568179,"remaining_time":4.585000754},
{"learn":[78228.32858],"iteration":75,"passed_time":0.3771493681,"remaining_time":4.585342317},
{"learn":[78071.03547],"iteration":76,"passed_time":0.3830737734,"remaining_time":4.591910296},
{"learn":[77947.19795],"iteration":77,"passed_time":0.3891905366,"remaining_time":4.600431727},
{"learn":[77806.4762],"iteration":78,"passed_time":0.3944428671,"remaining_time":4.598504818},
{"learn":[77505.00418],"iteration":79,"passed_time":0.3992439354,"remaining_time":4.591305257},
{"learn":[77414.89878],"iteration":80,"passed_time":0.4051006588,"remaining_time":4.596142043},
{"learn":[77160.98963],"iteration":81,"passed_time":0.4099630341,"remaining_time":4.589586163},
{"learn":[77067.71672],"iteration":82,"passed_time":0.4151630127,"remaining_time":4.586800996},
{"learn":[77005.32227],"iteration":83,"passed_time":0.4211318057,"remaining_time":4.592342072},
{"learn":[76941.37096],"iteration":84,"passed_time":0.4276438462,"remaining_time":4.603460227},
{"learn":[76719.15632],"iteration":85,"passed_time":0.4321302202,"remaining_time":4.592639782},
{"learn":[76599.01208],"iteration":86,"passed_time":0.4364665299,"remaining_time":4.580390135},
{"learn":[76400.02168],"iteration":87,"passed_time":0.4403473041,"remaining_time":4.563599334},
{"learn":[76315.94083],"iteration":88,"passed_time":0.4434799344,"remaining_time":4.539440677},
{"learn":[76286.74727],"iteration":89,"passed_time":0.4467112373,"remaining_time":4.516746955},
{"learn":[76148.76852],"iteration":90,"passed_time":0.450626553,"remaining_time":4.50131359},
{"learn":[76086.73766],"iteration":91,"passed_time":0.4540745111,"remaining_time":4.481518001},
{"learn":[75864.74197],"iteration":92,"passed_time":0.4688951193,"remaining_time":4.572987884},
{"learn":[75813.99533],"iteration":93,"passed_time":0.4753223578,"remaining_time":4.58129847},
{"learn":[75717.29057],"iteration":94,"passed_time":0.4806842139,"remaining_time":4.579149617},
{"learn":[75613.16207],"iteration":95,"passed_time":0.487375957,"remaining_time":4.589456929},
{"learn":[75564.6673],"iteration":96,"passed_time":0.4933257226,"remaining_time":4.592506469},
{"learn":[75524.85756],"iteration":97,"passed_time":0.5003694507,"remaining_time":4.605441271},
{"learn":[75484.61722],"iteration":98,"passed_time":0.5052332598,"remaining_time":4.598133001},
{"learn":[75280.34075],"iteration":99,"passed_time":0.511751429,"remaining_time":4.605762861},
{"learn":[75141.72209],"iteration":100,"passed_time":0.518010858,"remaining_time":4.610809518},
{"learn":[75050.89755],"iteration":101,"passed_time":0.525108723,"remaining_time":4.623016012},
{"learn":[74974.33244],"iteration":102,"passed_time":0.5332747521,"remaining_time":4.644150025},
{"learn":[74873.89324],"iteration":103,"passed_time":0.5396533488,"remaining_time":4.649321159},
{"learn":[74784.15613],"iteration":104,"passed_time":0.5443997458,"remaining_time":4.640359738},
{"learn":[74707.50112],"iteration":105,"passed_time":0.5489343982,"remaining_time":4.629692},
{"learn":[74620.89151],"iteration":106,"passed_time":0.5677551995,"remaining_time":4.73836816},
{"learn":[74559.3754],"iteration":107,"passed_time":0.5713904263,"remaining_time":4.719261669},
{"learn":[74526.26171],"iteration":108,"passed_time":0.5777795863,"remaining_time":4.722950563},
{"learn":[74496.40659],"iteration":109,"passed_time":0.5818670953,"remaining_time":4.707833771},
{"learn":[74356.97696],"iteration":110,"passed_time":0.5925013399,"remaining_time":4.745348569},
{"learn":[74237.93918],"iteration":111,"passed_time":0.6074144249,"remaining_time":4.815928655},
{"learn":[74198.91938],"iteration":112,"passed_time":0.6226881496,"remaining_time":4.887826449},
{"learn":[74181.38406],"iteration":113,"passed_time":0.6289233502,"remaining_time":4.887948143},
{"learn":[74134.41218],"iteration":114,"passed_time":0.6339818225,"remaining_time":4.878903591},
{"learn":[74102.35375],"iteration":115,"passed_time":0.6675870688,"remaining_time":5.087473869},
{"learn":[74025.20601],"iteration":116,"passed_time":0.6723927672,"remaining_time":5.074553961},
{"learn":[73970.89665],"iteration":117,"passed_time":0.6771825875,"remaining_time":5.0616529},
{"learn":[73936.62072],"iteration":118,"passed_time":0.6985043323,"remaining_time":5.171279972},
{"learn":[73876.04091],"iteration":119,"passed_time":0.7137346067,"remaining_time":5.234053783},
{"learn":[73827.6006],"iteration":120,"passed_time":0.7218106243,"remaining_time":5.243566436},
{"learn":[73813.41482],"iteration":121,"passed_time":0.7402667649,"remaining_time":5.327493603},
{"learn":[73713.22171],"iteration":122,"passed_time":0.745694813,"remaining_time":5.316864643},
{"learn":[73685.45157],"iteration":123,"passed_time":0.7554777473,"remaining_time":5.337084731},
{"learn":[73605.53793],"iteration":124,"passed_time":0.7776440749,"remaining_time":5.443508524},
{"learn":[73542.41992],"iteration":125,"passed_time":0.7882731645,"remaining_time":5.467863062},
{"learn":[73518.9366],"iteration":126,"passed_time":0.7966963085,"remaining_time":5.476502971},
{"learn":[73426.35004],"iteration":127,"passed_time":0.8066605094,"remaining_time":5.49537472},
{"learn":[73395.51211],"iteration":128,"passed_time":0.8165084521,"remaining_time":5.513014432},
{"learn":[73316.4955],"iteration":129,"passed_time":0.8231820133,"remaining_time":5.50898732},
{"learn":[73241.2656],"iteration":130,"passed_time":0.8300642988,"remaining_time":5.506304395},
{"learn":[73233.59518],"iteration":131,"passed_time":0.8473192006,"remaining_time":5.571765652},
{"learn":[73200.85327],"iteration":132,"passed_time":0.8560572401,"remaining_time":5.580463362},
{"learn":[73175.70894],"iteration":133,"passed_time":0.8625588502,"remaining_time":5.574447494},
{"learn":[73155.38946],"iteration":134,"passed_time":0.869180284,"remaining_time":5.56919219},
{"learn":[73120.99867],"iteration":135,"passed_time":0.8757324514,"remaining_time":5.56347675},
{"learn":[73031.6262],"iteration":136,"passed_time":0.8845559085,"remaining_time":5.572056562},
{"learn":[73006.37181],"iteration":137,"passed_time":0.8892230812,"remaining_time":5.554422435},
{"learn":[72938.42879],"iteration":138,"passed_time":0.8933950002,"remaining_time":5.53390716},
{"learn":[72855.17747],"iteration":139,"passed_time":0.8985313119,"remaining_time":5.519549487},
{"learn":[72769.66983],"iteration":140,"passed_time":0.9017257363,"remaining_time":5.493492252},
{"learn":[72693.34157],"iteration":141,"passed_time":0.9057270481,"remaining_time":5.472632445},
{"learn":[72654.65555],"iteration":142,"passed_time":0.9096541931,"remaining_time":5.45156394},
{"learn":[72608.59708],"iteration":143,"passed_time":0.9128465887,"remaining_time":5.426365833},
{"learn":[72601.49682],"iteration":144,"passed_time":0.9157488977,"remaining_time":5.399760742},
{"learn":[72554.39237],"iteration":145,"passed_time":0.9190371053,"remaining_time":5.375737588},
{"learn":[72533.20244],"iteration":146,"passed_time":0.922169764,"remaining_time":5.351093937},
{"learn":[72516.15654],"iteration":147,"passed_time":0.9246259381,"remaining_time":5.322846616},
{"learn":[72443.01066],"iteration":148,"passed_time":0.9278021538,"remaining_time":5.299057939},
{"learn":[72402.39928],"iteration":149,"passed_time":0.9320635334,"remaining_time":5.281693356},
{"learn":[72335.47963],"iteration":150,"passed_time":0.9357961939,"remaining_time":5.261529594},
{"learn":[72286.81953],"iteration":151,"passed_time":0.9491813087,"remaining_time":5.295432564},
{"learn":[72260.78091],"iteration":152,"passed_time":0.9520586572,"remaining_time":5.270546945},
{"learn":[72213.75752],"iteration":153,"passed_time":0.9551318694,"remaining_time":5.247023127},
{"learn":[72192.07864],"iteration":154,"passed_time":0.9582205005,"remaining_time":5.223847245},
{"learn":[72185.07401],"iteration":155,"passed_time":0.9607516957,"remaining_time":5.19791302},
{"learn":[72071.42037],"iteration":156,"passed_time":0.9663960964,"remaining_time":5.188993053},
{"learn":[72044.27056],"iteration":157,"passed_time":0.9712050079,"remaining_time":5.175662131},
{"learn":[71969.93869],"iteration":158,"passed_time":0.9801543522,"remaining_time":5.184338429},
{"learn":[71941.67511],"iteration":159,"passed_time":0.9837065572,"remaining_time":5.164459425},
{"learn":[71889.45449],"iteration":160,"passed_time":0.9971648781,"remaining_time":5.196405793},
{"learn":[71826.90989],"iteration":161,"passed_time":1.009925516,"remaining_time":5.224182606},
{"learn":[71796.42297],"iteration":162,"passed_time":1.013767631,"remaining_time":5.20566569},
{"learn":[71735.81134],"iteration":163,"passed_time":1.017853251,"remaining_time":5.18856901},
{"learn":[71676.97492],"iteration":164,"passed_time":1.023338357,"remaining_time":5.178712292},
{"learn":[71615.68297],"iteration":165,"passed_time":1.02680188,"remaining_time":5.158751615},
{"learn":[71565.58611],"iteration":166,"passed_time":1.030490242,"remaining_time":5.140110008},
{"learn":[71523.97813],"iteration":167,"passed_time":1.033692162,"remaining_time":5.119237372},
{"learn":[71489.56382],"iteration":168,"passed_time":1.040230805,"remaining_time":5.114981056},
{"learn":[71444.20539],"iteration":169,"passed_time":1.044643222,"remaining_time":5.100316907},
{"learn":[71401.46869],"iteration":170,"passed_time":1.048326541,"remaining_time":5.082238025},
{"learn":[71377.00261],"iteration":171,"passed_time":1.052195622,"remaining_time":5.065220785},
{"learn":[71335.57532],"iteration":172,"passed_time":1.071628674,"remaining_time":5.122756724},
{"learn":[71313.67648],"iteration":173,"passed_time":1.077023446,"remaining_time":5.112766475},
{"learn":[71288.09383],"iteration":174,"passed_time":1.102021546,"remaining_time":5.195244433},
{"learn":[71264.00739],"iteration":175,"passed_time":1.108773052,"remaining_time":5.191073833},
{"learn":[71217.24258],"iteration":176,"passed_time":1.114828497,"remaining_time":5.18363759},
{"learn":[71164.31965],"iteration":177,"passed_time":1.13315105,"remaining_time":5.232866083},
{"learn":[71112.75812],"iteration":178,"passed_time":1.141182012,"remaining_time":5.234136492},
{"learn":[71064.49669],"iteration":179,"passed_time":1.161444481,"remaining_time":5.291024858},
{"learn":[71035.83533],"iteration":180,"passed_time":1.166807944,"remaining_time":5.279644784},
{"learn":[71013.24045],"iteration":181,"passed_time":1.171566144,"remaining_time":5.265610473},
{"learn":[70985.80299],"iteration":182,"passed_time":1.190636666,"remaining_time":5.315574622},
{"learn":[70955.73137],"iteration":183,"passed_time":1.195848314,"remaining_time":5.303327307},
{"learn":[70935.67213],"iteration":184,"passed_time":1.200724733,"remaining_time":5.289679231},
{"learn":[70905.17705],"iteration":185,"passed_time":1.218548181,"remaining_time":5.332786124},
{"learn":[70888.48902],"iteration":186,"passed_time":1.223381643,"remaining_time":5.318766179},
{"learn":[70869.52775],"iteration":187,"passed_time":1.228512066,"remaining_time":5.306126582},
{"learn":[70824.0445],"iteration":188,"passed_time":1.232016387,"remaining_time":5.286588836},
{"learn":[70800.60084],"iteration":189,"passed_time":1.235457171,"remaining_time":5.266948992},
{"learn":[70792.55594],"iteration":190,"passed_time":1.238523824,"remaining_time":5.245894105},
{"learn":[70752.58891],"iteration":191,"passed_time":1.242233751,"remaining_time":5.2277337},
{"learn":[70707.25105],"iteration":192,"passed_time":1.245726853,"remaining_time":5.208816428},
{"learn":[70661.70575],"iteration":193,"passed_time":1.248491721,"remaining_time":5.187032613},
{"learn":[70636.39172],"iteration":194,"passed_time":1.251847758,"remaining_time":5.167884335},
{"learn":[70624.59598],"iteration":195,"passed_time":1.254647056,"remaining_time":5.146613434},
{"learn":[70596.35707],"iteration":196,"passed_time":1.257648352,"remaining_time":5.126353435},
{"learn":[70576.62638],"iteration":197,"passed_time":1.260638239,"remaining_time":5.106221555},
{"learn":[70524.19092],"iteration":198,"passed_time":1.26379463,"remaining_time":5.086932154},
{"learn":[70495.40961],"iteration":199,"passed_time":1.266386471,"remaining_time":5.065545886},
{"learn":[70478.60213],"iteration":200,"passed_time":1.269615464,"remaining_time":5.04687938},
{"learn":[70473.55632],"iteration":201,"passed_time":1.272494382,"remaining_time":5.026982757},
{"learn":[70457.81608],"iteration":202,"passed_time":1.276537542,"remaining_time":5.011824736},
{"learn":[70440.28727],"iteration":203,"passed_time":1.279236591,"remaining_time":4.991531011},
{"learn":[70421.23374],"iteration":204,"passed_time":1.281724833,"remaining_time":4.970591427},
{"learn":[70392.67118],"iteration":205,"passed_time":1.284517537,"remaining_time":4.951004488},
{"learn":[70375.3361],"iteration":206,"passed_time":1.28812708,"remaining_time":4.934709055},
{"learn":[70342.80598],"iteration":207,"passed_time":1.291935479,"remaining_time":4.919292787},
{"learn":[70307.5256],"iteration":208,"passed_time":1.301808245,"remaining_time":4.926939339},
{"learn":[70278.83371],"iteration":209,"passed_time":1.305302719,"remaining_time":4.910424514},
{"learn":[70264.36685],"iteration":210,"passed_time":1.308586342,"remaining_time":4.893244662},
{"learn":[70253.99296],"iteration":211,"passed_time":1.311853835,"remaining_time":4.876135953},
{"learn":[70243.57982],"iteration":212,"passed_time":1.315232271,"remaining_time":4.859567122},
{"learn":[70205.65827],"iteration":213,"passed_time":1.318799428,"remaining_time":4.843814723},
{"learn":[70172.26895],"iteration":214,"passed_time":1.322811625,"remaining_time":4.829800583},
{"learn":[70158.87518],"iteration":215,"passed_time":1.325778362,"remaining_time":4.812084424},
{"learn":[70156.48811],"iteration":216,"passed_time":1.329404103,"remaining_time":4.796882085},
{"learn":[70125.2698],"iteration":217,"passed_time":1.332922833,"remaining_time":4.781402088},
{"learn":[70087.0945],"iteration":218,"passed_time":1.336993432,"remaining_time":4.767999409},
{"learn":[70053.37259],"iteration":219,"passed_time":1.340840032,"remaining_time":4.753887386},
{"learn":[70022.98496],"iteration":220,"passed_time":1.34572498,"remaining_time":4.743528324},
{"learn":[70006.7191],"iteration":221,"passed_time":1.379343809,"remaining_time":4.833916592},
{"learn":[69993.47673],"iteration":222,"passed_time":1.384312984,"remaining_time":4.82336856},
{"learn":[69985.89229],"iteration":223,"passed_time":1.389223998,"remaining_time":4.812668851},
{"learn":[69970.54457],"iteration":224,"passed_time":1.395249241,"remaining_time":4.805858496},
{"learn":[69964.64199],"iteration":225,"passed_time":1.399666162,"remaining_time":4.793546944},
{"learn":[69945.97671],"iteration":226,"passed_time":1.40519141,"remaining_time":4.78507912},
{"learn":[69929.71587],"iteration":227,"passed_time":1.410700594,"remaining_time":4.776582713},
{"learn":[69908.58028],"iteration":228,"passed_time":1.416235923,"remaining_time":4.76820042},
{"learn":[69882.64361],"iteration":229,"passed_time":1.422679493,"remaining_time":4.76288352},
{"learn":[69874.75135],"iteration":230,"passed_time":1.42786673,"remaining_time":4.753374525},
{"learn":[69846.87465],"iteration":231,"passed_time":1.432578181,"remaining_time":4.742327773},
{"learn":[69835.29199],"iteration":232,"passed_time":1.437475662,"remaining_time":4.731947781},
{"learn":[69822.59147],"iteration":233,"passed_time":1.441699451,"remaining_time":4.719409315},
{"learn":[69798.08187],"iteration":234,"passed_time":1.447154166,"remaining_time":4.710948669},
{"learn":[69797.47792],"iteration":235,"passed_time":1.451170156,"remaining_time":4.697855929},
{"learn":[69781.56089],"iteration":236,"passed_time":1.455556161,"remaining_time":4.686031015},
{"learn":[69745.35346],"iteration":237,"passed_time":1.461637032,"remaining_time":4.679695034},
{"learn":[69738.27934],"iteration":238,"passed_time":1.466680402,"remaining_time":4.670057681},
{"learn":[69717.31298],"iteration":239,"passed_time":1.472037325,"remaining_time":4.66145153},
{"learn":[69678.42043],"iteration":240,"passed_time":1.477884676,"remaining_time":4.654416884},
{"learn":[69676.93053],"iteration":241,"passed_time":1.482397932,"remaining_time":4.643213357},
{"learn":[69649.74041],"iteration":242,"passed_time":1.48710017,"remaining_time":4.632653616},
{"learn":[69635.44946],"iteration":243,"passed_time":1.492764278,"remaining_time":4.625122108},
{"learn":[69615.81171],"iteration":244,"passed_time":1.497365247,"remaining_time":4.614329639},
{"learn":[69583.65725],"iteration":245,"passed_time":1.502755975,"remaining_time":4.60600815},
{"learn":[69565.26075],"iteration":246,"passed_time":1.508189016,"remaining_time":4.59783939},
{"learn":[69539.44903],"iteration":247,"passed_time":1.512153298,"remaining_time":4.585239033},
{"learn":[69512.93445],"iteration":248,"passed_time":1.515918185,"remaining_time":4.572106656},
{"learn":[69492.36423],"iteration":249,"passed_time":1.521227421,"remaining_time":4.563682264},
{"learn":[69469.83263],"iteration":250,"passed_time":1.524936533,"remaining_time":4.550507822},
{"learn":[69446.01911],"iteration":251,"passed_time":1.529138902,"remaining_time":4.538872614},
{"learn":[69427.18119],"iteration":252,"passed_time":1.533384327,"remaining_time":4.527423289},
{"learn":[69402.31269],"iteration":253,"passed_time":1.539367055,"remaining_time":4.521133163},
{"learn":[69395.35768],"iteration":254,"passed_time":1.543753507,"remaining_time":4.510181814},
{"learn":[69368.44266],"iteration":255,"passed_time":1.547981743,"remaining_time":4.498821939},
{"learn":[69355.94211],"iteration":256,"passed_time":1.552704965,"remaining_time":4.488948595},
{"learn":[69354.35185],"iteration":257,"passed_time":1.556749651,"remaining_time":4.477163725},
{"learn":[69329.07449],"iteration":258,"passed_time":1.561133588,"remaining_time":4.466409223},
{"learn":[69321.39704],"iteration":259,"passed_time":1.565276055,"remaining_time":4.455016464},
{"learn":[69286.11765],"iteration":260,"passed_time":1.56881233,"remaining_time":4.441962882},
{"learn":[69249.01387],"iteration":261,"passed_time":1.573751138,"remaining_time":4.432932596},
{"learn":[69222.56297],"iteration":262,"passed_time":1.578056169,"remaining_time":4.422157402},
{"learn":[69208.43356],"iteration":263,"passed_time":1.582498688,"remaining_time":4.411814524},
{"learn":[69173.12162],"iteration":264,"passed_time":1.586900367,"remaining_time":4.401402904},
{"learn":[69160.80936],"iteration":265,"passed_time":1.590957776,"remaining_time":4.390086495},
{"learn":[69139.63257],"iteration":266,"passed_time":1.595415755,"remaining_time":4.379924152},
{"learn":[69118.68849],"iteration":267,"passed_time":1.599127253,"remaining_time":4.367765482},
{"learn":[69103.52012],"iteration":268,"passed_time":1.603472378,"remaining_time":4.35739148},
{"learn":[69084.80292],"iteration":269,"passed_time":1.607154744,"remaining_time":4.345270235},
{"learn":[69079.92804],"iteration":270,"passed_time":1.610193936,"remaining_time":4.331481105},
{"learn":[69066.86892],"iteration":271,"passed_time":1.612894473,"remaining_time":4.316864618},
{"learn":[69050.22946],"iteration":272,"passed_time":1.615892151,"remaining_time":4.303126717},
{"learn":[69035.90655],"iteration":273,"passed_time":1.619538243,"remaining_time":4.291185272},
{"learn":[69022.32103],"iteration":274,"passed_time":1.623515561,"remaining_time":4.280177388},
{"learn":[68995.7716],"iteration":275,"passed_time":1.626865357,"remaining_time":4.267574342},
{"learn":[68970.08609],"iteration":276,"passed_time":1.629570387,"remaining_time":4.253355198},
{"learn":[68942.08401],"iteration":277,"passed_time":1.633110104,"remaining_time":4.241386673},
{"learn":[68921.38935],"iteration":278,"passed_time":1.636731104,"remaining_time":4.229688623},
{"learn":[68899.08161],"iteration":279,"passed_time":1.639548855,"remaining_time":4.215982769},
{"learn":[68891.34535],"iteration":280,"passed_time":1.643296143,"remaining_time":4.204732835},
{"learn":[68867.97734],"iteration":281,"passed_time":1.646442904,"remaining_time":4.19200711},
{"learn":[68827.01283],"iteration":282,"passed_time":1.649021043,"remaining_time":4.177908437},
{"learn":[68814.80967],"iteration":283,"passed_time":1.652222829,"remaining_time":4.165463187},
{"learn":[68785.07585],"iteration":284,"passed_time":1.655203612,"remaining_time":4.152528359},
{"learn":[68749.48663],"iteration":285,"passed_time":1.658366514,"remaining_time":4.1401178},
{"learn":[68745.28151],"iteration":286,"passed_time":1.661584861,"remaining_time":4.127909428},
{"learn":[68719.65752],"iteration":287,"passed_time":1.665142109,"remaining_time":4.116601324},
{"learn":[68705.7544],"iteration":288,"passed_time":1.668672231,"remaining_time":4.105280126},
{"learn":[68685.35251],"iteration":289,"passed_time":1.671954418,"remaining_time":4.093405644},
{"learn":[68672.74872],"iteration":290,"passed_time":1.675349007,"remaining_time":4.081864076},
{"learn":[68662.69845],"iteration":291,"passed_time":1.678552279,"remaining_time":4.069914431},
{"learn":[68629.42612],"iteration":292,"passed_time":1.682308273,"remaining_time":4.059358188},
{"learn":[68607.47375],"iteration":293,"passed_time":1.685502208,"remaining_time":4.047498499},
{"learn":[68586.08781],"iteration":294,"passed_time":1.68881692,"remaining_time":4.035986198},
{"learn":[68567.98866],"iteration":295,"passed_time":1.69198591,"remaining_time":4.024182705},
{"learn":[68556.01093],"iteration":296,"passed_time":1.695692792,"remaining_time":4.013710547},
{"learn":[68538.6483],"iteration":297,"passed_time":1.698648039,"remaining_time":4.001513166},
{"learn":[68534.48508],"iteration":298,"passed_time":1.702173447,"remaining_time":3.990714335},
{"learn":[68528.40754],"iteration":299,"passed_time":1.705169951,"remaining_time":3.978729885},
{"learn":[68513.12444],"iteration":300,"passed_time":1.708042091,"remaining_time":3.966516351},
{"learn":[68489.2453],"iteration":301,"passed_time":1.711393997,"remaining_time":3.955473543},
{"learn":[68487.67087],"iteration":302,"passed_time":1.714391823,"remaining_time":3.943666999},
{"learn":[68450.24403],"iteration":303,"passed_time":1.717789393,"remaining_time":3.932833609},
{"learn":[68440.86717],"iteration":304,"passed_time":1.72115217,"remaining_time":3.921969699},
{"learn":[68431.31612],"iteration":305,"passed_time":1.724618749,"remaining_time":3.911390234},
{"learn":[68422.56373],"iteration":306,"passed_time":1.728439926,"remaining_time":3.901657552},
{"learn":[68399.51806],"iteration":307,"passed_time":1.731250805,"remaining_time":3.889693367},
{"learn":[68381.84703],"iteration":308,"passed_time":1.734142119,"remaining_time":3.877968299},
{"learn":[68372.26975],"iteration":309,"passed_time":1.737272517,"remaining_time":3.866832377},
{"learn":[68352.27847],"iteration":310,"passed_time":1.757616909,"remaining_time":3.893884406},
{"learn":[68339.21987],"iteration":311,"passed_time":1.763245541,"remaining_time":3.888182475},
{"learn":[68323.32828],"iteration":312,"passed_time":1.76941689,"remaining_time":3.883672215},
{"learn":[68309.59017],"iteration":313,"passed_time":1.775505324,"remaining_time":3.878970229},
{"learn":[68301.19833],"iteration":314,"passed_time":1.780932085,"remaining_time":3.872820566},
{"learn":[68283.62117],"iteration":315,"passed_time":1.803282637,"remaining_time":3.903307987},
{"learn":[68265.811],"iteration":316,"passed_time":1.809281339,"remaining_time":3.898230772},
{"learn":[68246.81659],"iteration":317,"passed_time":1.817135548,"remaining_time":3.897127182},
{"learn":[68233.82834],"iteration":318,"passed_time":1.823839941,"remaining_time":3.893526645},
{"learn":[68222.76183],"iteration":319,"passed_time":1.830477643,"remaining_time":3.889764992},
{"learn":[68206.61838],"iteration":320,"passed_time":1.837312863,"remaining_time":3.886403221},
{"learn":[68190.25517],"iteration":321,"passed_time":1.843817504,"remaining_time":3.882323813},
{"learn":[68173.52726],"iteration":322,"passed_time":1.8489074,"remaining_time":3.875264117},
{"learn":[68162.64757],"iteration":323,"passed_time":1.854543082,"remaining_time":3.869355319},
{"learn":[68140.76902],"iteration":324,"passed_time":1.86124069,"remaining_time":3.865653741},
{"learn":[68132.74594],"iteration":325,"passed_time":1.866472554,"remaining_time":3.858903379},
{"learn":[68118.05027],"iteration":326,"passed_time":1.871971841,"remaining_time":3.852712688},
{"learn":[68109.35718],"iteration":327,"passed_time":1.878416625,"remaining_time":3.84846333},
{"learn":[68105.95483],"iteration":328,"passed_time":1.883395496,"remaining_time":3.841210874},
{"learn":[68096.68077],"iteration":329,"passed_time":1.888571814,"remaining_time":3.834373076},
{"learn":[68087.53768],"iteration":330,"passed_time":1.893231012,"remaining_time":3.826500142},
{"learn":[68081.13232],"iteration":331,"passed_time":1.900996174,"remaining_time":3.824895916},
{"learn":[68075.00548],"iteration":332,"passed_time":1.905543786,"remaining_time":3.816809925},
{"learn":[68056.5052],"iteration":333,"passed_time":1.910601522,"remaining_time":3.809762316},
{"learn":[68044.81364],"iteration":334,"passed_time":1.914814357,"remaining_time":3.801049394},
{"learn":[68010.99108],"iteration":335,"passed_time":1.919408111,"remaining_time":3.793116029},
{"learn":[67988.8773],"iteration":336,"passed_time":1.924793806,"remaining_time":3.786760514},
{"learn":[67978.43999],"iteration":337,"passed_time":1.929543188,"remaining_time":3.779164469},
{"learn":[67969.62519],"iteration":338,"passed_time":1.933827711,"remaining_time":3.770678811},
{"learn":[67961.09333],"iteration":339,"passed_time":1.937887212,"remaining_time":3.761781058},
{"learn":[67937.09956],"iteration":340,"passed_time":1.942600695,"remaining_time":3.754175536},
{"learn":[67921.69162],"iteration":341,"passed_time":1.946910085,"remaining_time":3.745809462},
{"learn":[67902.30553],"iteration":342,"passed_time":1.951233327,"remaining_time":3.737493573},
{"learn":[67881.27008],"iteration":343,"passed_time":1.955918131,"remaining_time":3.729890389},
{"learn":[67872.8608],"iteration":344,"passed_time":1.960461377,"remaining_time":3.722035368},
{"learn":[67860.646],"iteration":345,"passed_time":1.964924843,"remaining_time":3.714048692},
{"learn":[67847.58118],"iteration":346,"passed_time":1.968196279,"remaining_time":3.703839108},
{"learn":[67829.78103],"iteration":347,"passed_time":1.972493921,"remaining_time":3.695592058},
{"learn":[67820.93212],"iteration":348,"passed_time":1.976052909,"remaining_time":3.68598981},
{"learn":[67811.61764],"iteration":349,"passed_time":1.998700344,"remaining_time":3.711872068},
{"learn":[67801.41971],"iteration":350,"passed_time":2.004374156,"remaining_time":3.706093525},
{"learn":[67786.52574],"iteration":351,"passed_time":2.011031936,"remaining_time":3.702126973},
{"learn":[67771.27844],"iteration":352,"passed_time":2.017420684,"remaining_time":3.697652075},
{"learn":[67757.78638],"iteration":353,"passed_time":2.023930921,"remaining_time":3.693388064},
{"learn":[67753.77845],"iteration":354,"passed_time":2.029193909,"remaining_time":3.686845271},
{"learn":[67744.06926],"iteration":355,"passed_time":2.034505953,"remaining_time":3.68039841},
{"learn":[67736.71137],"iteration":356,"passed_time":2.039842028,"remaining_time":3.674001187},
{"learn":[67722.83503],"iteration":357,"passed_time":2.045496829,"remaining_time":3.668181464},
{"learn":[67714.1564],"iteration":358,"passed_time":2.050283789,"remaining_time":3.660813117},
{"learn":[67699.85864],"iteration":359,"passed_time":2.056867672,"remaining_time":3.656653639},
{"learn":[67687.65852],"iteration":360,"passed_time":2.061794903,"remaining_time":3.649548319},
{"learn":[67680.07054],"iteration":361,"passed_time":2.067665127,"remaining_time":3.644116992},
{"learn":[67667.97709],"iteration":362,"passed_time":2.073484136,"remaining_time":3.638593374},
{"learn":[67659.04623],"iteration":363,"passed_time":2.079770931,"remaining_time":3.633885473},
{"learn":[67638.06581],"iteration":364,"passed_time":2.086666824,"remaining_time":3.630228585},
{"learn":[67627.65019],"iteration":365,"passed_time":2.09180499,"remaining_time":3.623509191},
{"learn":[67613.85068],"iteration":366,"passed_time":2.099603504,"remaining_time":3.621386971},
{"learn":[67596.67223],"iteration":367,"passed_time":2.105388911,"remaining_time":3.615776609},
{"learn":[67585.40011],"iteration":368,"passed_time":2.111990108,"remaining_time":3.61156032},
{"learn":[67573.59671],"iteration":369,"passed_time":2.11779609,"remaining_time":3.605977126},
{"learn":[67547.20051],"iteration":370,"passed_time":2.123658029,"remaining_time":3.600487602},
{"learn":[67541.12311],"iteration":371,"passed_time":2.130004157,"remaining_time":3.595813469},
{"learn":[67524.69158],"iteration":372,"passed_time":2.143907406,"remaining_time":3.603833628},
{"learn":[67515.1597],"iteration":373,"passed_time":2.148476774,"remaining_time":3.596113531},
{"learn":[67494.86033],"iteration":374,"passed_time":2.153599172,"remaining_time":3.589331953},
{"learn":[67479.19476],"iteration":375,"passed_time":2.157019169,"remaining_time":3.579733941},
{"learn":[67459.57638],"iteration":376,"passed_time":2.174735193,"remaining_time":3.59379317},
{"learn":[67450.29598],"iteration":377,"passed_time":2.180382528,"remaining_time":3.587825219},
{"learn":[67439.90576],"iteration":378,"passed_time":2.18588288,"remaining_time":3.581618123},
{"learn":[67429.63889],"iteration":379,"passed_time":2.190249247,"remaining_time":3.573564562},
{"learn":[67410.41473],"iteration":380,"passed_time":2.195107467,"remaining_time":3.566329454},
{"learn":[67394.73046],"iteration":381,"passed_time":2.199702092,"remaining_time":3.558680348},
{"learn":[67375.5217],"iteration":382,"passed_time":2.204047105,"remaining_time":3.550645076},
{"learn":[67359.66631],"iteration":383,"passed_time":2.207627482,"remaining_time":3.54140242},
{"learn":[67353.62642],"iteration":384,"passed_time":2.21079543,"remaining_time":3.531530361},
{"learn":[67343.17591],"iteration":385,"passed_time":2.213841012,"remaining_time":3.521498397},
{"learn":[67331.37684],"iteration":386,"passed_time":2.217460357,"remaining_time":3.512411366},
{"learn":[67314.99844],"iteration":387,"passed_time":2.220557509,"remaining_time":3.502528855},
{"learn":[67306.96363],"iteration":388,"passed_time":2.223612163,"remaining_time":3.492614477},
{"learn":[67289.60315],"iteration":389,"passed_time":2.22645755,"remaining_time":3.482407963},
{"learn":[67282.51952],"iteration":390,"passed_time":2.229087114,"remaining_time":3.471902948},
{"learn":[67262.97702],"iteration":391,"passed_time":2.232172314,"remaining_time":3.462144813},
{"learn":[67251.03086],"iteration":392,"passed_time":2.234996064,"remaining_time":3.452016821},
{"learn":[67243.05621],"iteration":393,"passed_time":2.238138867,"remaining_time":3.442416633},
{"learn":[67232.00392],"iteration":394,"passed_time":2.241344133,"remaining_time":3.432944812},
{"learn":[67216.41823],"iteration":395,"passed_time":2.244044879,"remaining_time":3.422735119},
{"learn":[67207.29503],"iteration":396,"passed_time":2.247143499,"remaining_time":3.413167581},
{"learn":[67191.98469],"iteration":397,"passed_time":2.250586094,"remaining_time":3.404152835},
{"learn":[67185.53499],"iteration":398,"passed_time":2.253980829,"remaining_time":3.39509393},
{"learn":[67180.16128],"iteration":399,"passed_time":2.257269615,"remaining_time":3.385904422},
{"learn":[67169.25492],"iteration":400,"passed_time":2.260557001,"remaining_time":3.376742253},
{"learn":[67157.45756],"iteration":401,"passed_time":2.263675144,"remaining_time":3.367357553},
{"learn":[67148.87591],"iteration":402,"passed_time":2.266804099,"remaining_time":3.358019968},
{"learn":[67134.38516],"iteration":403,"passed_time":2.270835418,"remaining_time":3.350044329},
{"learn":[67124.52416],"iteration":404,"passed_time":2.273999969,"remaining_time":3.340814769},
{"learn":[67101.30933],"iteration":405,"passed_time":2.277340582,"remaining_time":3.331872674},
{"learn":[67093.24893],"iteration":406,"passed_time":2.280361382,"remaining_time":3.322492137},
{"learn":[67085.78957],"iteration":407,"passed_time":2.282864391,"remaining_time":3.312391469},
{"learn":[67062.63687],"iteration":408,"passed_time":2.286774002,"remaining_time":3.304360477},
{"learn":[67051.28898],"iteration":409,"passed_time":2.289896242,"remaining_time":3.295216544},
{"learn":[67038.32107],"iteration":410,"passed_time":2.292961752,"remaining_time":3.286020613},
{"learn":[67031.63436],"iteration":411,"passed_time":2.295556652,"remaining_time":3.276182795},
{"learn":[67012.89346],"iteration":412,"passed_time":2.298351085,"remaining_time":3.266663648},
{"learn":[66998.3914],"iteration":413,"passed_time":2.302612003,"remaining_time":3.259252738},
{"learn":[66992.15711],"iteration":414,"passed_time":2.305558562,"remaining_time":3.250004239},
{"learn":[66972.3486],"iteration":415,"passed_time":2.308539347,"remaining_time":3.240834084},
{"learn":[66956.18407],"iteration":416,"passed_time":2.311209175,"remaining_time":3.23125887},
{"learn":[66943.64406],"iteration":417,"passed_time":2.314153035,"remaining_time":3.222098245},
{"learn":[66925.67227],"iteration":418,"passed_time":2.317001553,"remaining_time":3.212835089},
{"learn":[66920.53769],"iteration":419,"passed_time":2.319844418,"remaining_time":3.203594672},
{"learn":[66902.98234],"iteration":420,"passed_time":2.322616799,"remaining_time":3.194287712},
{"learn":[66889.9904],"iteration":421,"passed_time":2.325322981,"remaining_time":3.184921049},
{"learn":[66871.76392],"iteration":422,"passed_time":2.32833379,"remaining_time":3.176001411},
{"learn":[66865.4875],"iteration":423,"passed_time":2.332291522,"remaining_time":3.16839603},
{"learn":[66847.73102],"iteration":424,"passed_time":2.335306643,"remaining_time":3.159532517},
{"learn":[66836.55629],"iteration":425,"passed_time":2.338000003,"remaining_time":3.150262915},
{"learn":[66825.8861],"iteration":426,"passed_time":2.340786242,"remaining_time":3.141148751},
{"learn":[66811.59009],"iteration":427,"passed_time":2.343566881,"remaining_time":3.132056673},
{"learn":[66804.35803],"iteration":428,"passed_time":2.363800696,"remaining_time":3.146224236},
{"learn":[66795.77759],"iteration":429,"passed_time":2.367727527,"remaining_time":3.138615559},
{"learn":[66780.57605],"iteration":430,"passed_time":2.371486507,"remaining_time":3.130802372},
{"learn":[66769.1836],"iteration":431,"passed_time":2.376164504,"remaining_time":3.124216292},
{"learn":[66764.33297],"iteration":432,"passed_time":2.381877267,"remaining_time":3.11899402},
{"learn":[66751.18034],"iteration":433,"passed_time":2.38731644,"remaining_time":3.113412685},
{"learn":[66741.14729],"iteration":434,"passed_time":2.393889241,"remaining_time":3.109304416},
{"learn":[66718.03578],"iteration":435,"passed_time":2.399502435,"remaining_time":3.103943517},
{"learn":[66706.42396],"iteration":436,"passed_time":2.404488199,"remaining_time":3.097773126},
{"learn":[66695.01466],"iteration":437,"passed_time":2.411519106,"remaining_time":3.094232277},
{"learn":[66682.20548],"iteration":438,"passed_time":2.416109368,"remaining_time":3.087556618},
{"learn":[66677.10879],"iteration":439,"passed_time":2.421416577,"remaining_time":3.081802916},
{"learn":[66672.67775],"iteration":440,"passed_time":2.425713305,"remaining_time":3.074770379},
{"learn":[66666.15313],"iteration":441,"passed_time":2.430341494,"remaining_time":3.068168673},
{"learn":[66647.11421],"iteration":442,"passed_time":2.434344369,"remaining_time":3.060789647},
{"learn":[66639.74282],"iteration":443,"passed_time":2.437960614,"remaining_time":3.052941669},
{"learn":[66614.7101],"iteration":444,"passed_time":2.441693308,"remaining_time":3.045257946},
{"learn":[66609.18434],"iteration":445,"passed_time":2.444924909,"remaining_time":3.036969505},
{"learn":[66597.00981],"iteration":446,"passed_time":2.448062764,"remaining_time":3.028587715},
{"learn":[66586.86651],"iteration":447,"passed_time":2.451444813,"remaining_time":3.020530216},
{"learn":[66575.66069],"iteration":448,"passed_time":2.468317054,"remaining_time":3.029048322},
{"learn":[66564.04903],"iteration":449,"passed_time":2.47157377,"remaining_time":3.020812385},
{"learn":[66555.21447],"iteration":450,"passed_time":2.474632239,"remaining_time":3.012357204},
{"learn":[66542.78618],"iteration":451,"passed_time":2.477889491,"remaining_time":3.004166905},
{"learn":[66538.15559],"iteration":452,"passed_time":2.480491922,"remaining_time":2.995207685},
{"learn":[66532.90062],"iteration":453,"passed_time":2.483265901,"remaining_time":2.98648278},
{"learn":[66516.91341],"iteration":454,"passed_time":2.486260381,"remaining_time":2.978048148},
{"learn":[66497.30689],"iteration":455,"passed_time":2.489599482,"remaining_time":2.970048505},
{"learn":[66485.6282],"iteration":456,"passed_time":2.492742067,"remaining_time":2.96183576},
{"learn":[66473.71281],"iteration":457,"passed_time":2.496946925,"remaining_time":2.954902256},
{"learn":[66452.92595],"iteration":458,"passed_time":2.500200099,"remaining_time":2.946858941},
{"learn":[66434.65317],"iteration":459,"passed_time":2.503412894,"remaining_time":2.938789049},
{"learn":[66427.09456],"iteration":460,"passed_time":2.507159083,"remaining_time":2.931363874},
{"learn":[66411.95554],"iteration":461,"passed_time":2.512526612,"remaining_time":2.925842678},
{"learn":[66393.56512],"iteration":462,"passed_time":2.516067664,"remaining_time":2.918203748},
{"learn":[66384.83894],"iteration":463,"passed_time":2.519325799,"remaining_time":2.910255665},
{"learn":[66358.77558],"iteration":464,"passed_time":2.523340122,"remaining_time":2.903197775},
{"learn":[66352.13935],"iteration":465,"passed_time":2.542419407,"remaining_time":2.91341623},
{"learn":[66346.12286],"iteration":466,"passed_time":2.54542423,"remaining_time":2.905162987},
{"learn":[66332.75742],"iteration":467,"passed_time":2.548150748,"remaining_time":2.896615808},
{"learn":[66324.10963],"iteration":468,"passed_time":2.551004077,"remaining_time":2.888237026},
{"learn":[66317.59059],"iteration":469,"passed_time":2.553657892,"remaining_time":2.879656772},
{"learn":[66305.34992],"iteration":470,"passed_time":2.556593989,"remaining_time":2.871418727},
{"learn":[66295.77316],"iteration":471,"passed_time":2.559927033,"remaining_time":2.86364719},
{"learn":[66286.31648],"iteration":472,"passed_time":2.563043547,"remaining_time":2.855653169},
{"learn":[66273.01937],"iteration":473,"passed_time":2.565540472,"remaining_time":2.84699217},
{"learn":[66262.66815],"iteration":474,"passed_time":2.567968725,"remaining_time":2.838281223},
{"learn":[66254.8233],"iteration":475,"passed_time":2.571690311,"remaining_time":2.831020426},
{"learn":[66247.81169],"iteration":476,"passed_time":2.588609236,"remaining_time":2.838244509},
{"learn":[66238.09674],"iteration":477,"passed_time":2.591854348,"remaining_time":2.830435083},
{"learn":[66227.9975],"iteration":478,"passed_time":2.594875912,"remaining_time":2.822401567},
{"learn":[66211.37738],"iteration":479,"passed_time":2.597510459,"remaining_time":2.813969664},
{"learn":[66200.0751],"iteration":480,"passed_time":2.6002729,"remaining_time":2.805699865},
{"learn":[66183.16625],"iteration":481,"passed_time":2.603116231,"remaining_time":2.79753985},
{"learn":[66167.90665],"iteration":482,"passed_time":2.605579815,"remaining_time":2.788995371},
{"learn":[66156.0378],"iteration":483,"passed_time":2.608146395,"remaining_time":2.780585826},
{"learn":[66151.44966],"iteration":484,"passed_time":2.610577542,"remaining_time":2.772056565},
{"learn":[66140.91914],"iteration":485,"passed_time":2.613575609,"remaining_time":2.764151982},
{"learn":[66131.99961],"iteration":486,"passed_time":2.617267862,"remaining_time":2.756998795},
{"learn":[66123.73459],"iteration":487,"passed_time":2.620623675,"remaining_time":2.749506806},
{"learn":[66118.9896],"iteration":488,"passed_time":2.623631502,"remaining_time":2.741668093},
{"learn":[66108.27757],"iteration":489,"passed_time":2.626732255,"remaining_time":2.733945816},
{"learn":[66092.86032],"iteration":490,"passed_time":2.630062588,"remaining_time":2.726480361},
{"learn":[66081.46045],"iteration":491,"passed_time":2.634219224,"remaining_time":2.71988489},
{"learn":[66068.66985],"iteration":492,"passed_time":2.637729282,"remaining_time":2.712634373},
{"learn":[66053.08426],"iteration":493,"passed_time":2.640491012,"remaining_time":2.704632494},
{"learn":[66044.62606],"iteration":494,"passed_time":2.64351921,"remaining_time":2.696923638},
{"learn":[66034.19045],"iteration":495,"passed_time":2.646588616,"remaining_time":2.689275529},
{"learn":[66019.7846],"iteration":496,"passed_time":2.649926834,"remaining_time":2.681917902},
{"learn":[66015.61052],"iteration":497,"passed_time":2.653382771,"remaining_time":2.674695083},
{"learn":[66006.32777],"iteration":498,"passed_time":2.665143025,"remaining_time":2.675824961},
{"learn":[65997.81365],"iteration":499,"passed_time":2.668409561,"remaining_time":2.668409561},
{"learn":[65997.4534],"iteration":500,"passed_time":2.671349849,"remaining_time":2.660685778},
{"learn":[65990.48822],"iteration":501,"passed_time":2.684627172,"remaining_time":2.66323572},
{"learn":[65983.97435],"iteration":502,"passed_time":2.690405223,"remaining_time":2.658312914},
{"learn":[65973.94031],"iteration":503,"passed_time":2.695693777,"remaining_time":2.652904987},
{"learn":[65966.25807],"iteration":504,"passed_time":2.699821752,"remaining_time":2.646359935},
{"learn":[65952.31335],"iteration":505,"passed_time":2.704449468,"remaining_time":2.640312327},
{"learn":[65936.26366],"iteration":506,"passed_time":2.708907386,"remaining_time":2.634105209},
{"learn":[65922.3242],"iteration":507,"passed_time":2.713791931,"remaining_time":2.628318169},
{"learn":[65917.07962],"iteration":508,"passed_time":2.717671679,"remaining_time":2.621565411},
{"learn":[65910.86174],"iteration":509,"passed_time":2.723832827,"remaining_time":2.617015853},
{"learn":[65905.31356],"iteration":510,"passed_time":2.728869658,"remaining_time":2.611384076},
{"learn":[65892.89267],"iteration":511,"passed_time":2.733654991,"remaining_time":2.605514913},
{"learn":[65882.27842],"iteration":512,"passed_time":2.73780625,"remaining_time":2.599048039},
{"learn":[65875.14913],"iteration":513,"passed_time":2.742030135,"remaining_time":2.592658844},
{"learn":[65869.95055],"iteration":514,"passed_time":2.764220126,"remaining_time":2.603197594},
{"learn":[65864.34527],"iteration":515,"passed_time":2.769912829,"remaining_time":2.598135289},
{"learn":[65851.62812],"iteration":516,"passed_time":2.776850606,"remaining_time":2.594233738},
{"learn":[65844.08508],"iteration":517,"passed_time":2.783732574,"remaining_time":2.590268535},
{"learn":[65835.10769],"iteration":518,"passed_time":2.790216673,"remaining_time":2.585923352},
{"learn":[65828.46083],"iteration":519,"passed_time":2.795244844,"remaining_time":2.580226009},
{"learn":[65815.08414],"iteration":520,"passed_time":2.801160783,"remaining_time":2.575347437},
{"learn":[65808.80609],"iteration":521,"passed_time":2.807793455,"remaining_time":2.57112121},
{"learn":[65804.72441],"iteration":522,"passed_time":2.813125163,"remaining_time":2.56569924},
{"learn":[65798.57846],"iteration":523,"passed_time":2.819093725,"remaining_time":2.560856132},
{"learn":[65794.34021],"iteration":524,"passed_time":2.823886985,"remaining_time":2.554945367},
{"learn":[65770.91664],"iteration":525,"passed_time":2.829314966,"remaining_time":2.549610825},
{"learn":[65758.23719],"iteration":526,"passed_time":2.834421323,"remaining_time":2.54398726},
{"learn":[65746.36087],"iteration":527,"passed_time":2.840267286,"remaining_time":2.539026816},
{"learn":[65733.37709],"iteration":528,"passed_time":2.84545906,"remaining_time":2.533480562},
{"learn":[65725.76054],"iteration":529,"passed_time":2.849784017,"remaining_time":2.527166958},
{"learn":[65716.15691],"iteration":530,"passed_time":2.855646292,"remaining_time":2.522218665},
{"learn":[65704.50985],"iteration":531,"passed_time":2.861077682,"remaining_time":2.516887885},
{"learn":[65698.94089],"iteration":532,"passed_time":2.866444584,"remaining_time":2.511500227},
{"learn":[65687.01969],"iteration":533,"passed_time":2.871517778,"remaining_time":2.505856338},
{"learn":[65680.26852],"iteration":534,"passed_time":2.877091063,"remaining_time":2.500649241},
{"learn":[65674.38499],"iteration":535,"passed_time":2.881784431,"remaining_time":2.49467906},
{"learn":[65660.81567],"iteration":536,"passed_time":2.885897008,"remaining_time":2.488212877},
{"learn":[65646.19349],"iteration":537,"passed_time":2.891364831,"remaining_time":2.482919242},
{"learn":[65635.84507],"iteration":538,"passed_time":2.896151953,"remaining_time":2.477042765},
{"learn":[65629.28904],"iteration":539,"passed_time":2.901161785,"remaining_time":2.471360039},
{"learn":[65619.17583],"iteration":540,"passed_time":2.905747796,"remaining_time":2.465320219},
{"learn":[65607.31585],"iteration":541,"passed_time":2.910169496,"remaining_time":2.459146917},
{"learn":[65599.31344],"iteration":542,"passed_time":2.914754819,"remaining_time":2.453117776},
{"learn":[65589.52857],"iteration":543,"passed_time":2.920312903,"remaining_time":2.447909345},
{"learn":[65579.95922],"iteration":544,"passed_time":2.925341698,"remaining_time":2.442257747},
{"learn":[65570.57587],"iteration":545,"passed_time":2.93017563,"remaining_time":2.436446403},
{"learn":[65555.28733],"iteration":546,"passed_time":2.934728928,"remaining_time":2.430406224},
{"learn":[65544.29168],"iteration":547,"passed_time":2.938512668,"remaining_time":2.423736726},
{"learn":[65529.79483],"iteration":548,"passed_time":2.942549008,"remaining_time":2.417285251},
{"learn":[65522.16498],"iteration":549,"passed_time":2.947151262,"remaining_time":2.411305578},
{"learn":[65507.74407],"iteration":550,"passed_time":2.952334507,"remaining_time":2.405804344},
{"learn":[65501.9431],"iteration":551,"passed_time":2.956282122,"remaining_time":2.399301432},
{"learn":[65492.67763],"iteration":552,"passed_time":2.977127704,"remaining_time":2.406466698},
{"learn":[65482.08877],"iteration":553,"passed_time":2.983472686,"remaining_time":2.401857072},
{"learn":[65472.97118],"iteration":554,"passed_time":2.989673114,"remaining_time":2.397125289},
{"learn":[65459.95377],"iteration":555,"passed_time":2.995154693,"remaining_time":2.391814179},
{"learn":[65448.21382],"iteration":556,"passed_time":3.00049358,"remaining_time":2.386388969},
{"learn":[65442.18471],"iteration":557,"passed_time":3.0058778,"remaining_time":2.380999978},
{"learn":[65432.5902],"iteration":558,"passed_time":3.011266877,"remaining_time":2.375614835},
{"learn":[65425.62582],"iteration":559,"passed_time":3.016202721,"remaining_time":2.369873566},
{"learn":[65418.32644],"iteration":560,"passed_time":3.023054084,"remaining_time":2.365634123},
{"learn":[65407.05756],"iteration":561,"passed_time":3.028423256,"remaining_time":2.360230225},
{"learn":[65400.06294],"iteration":562,"passed_time":3.034361735,"remaining_time":2.355268345},
{"learn":[65390.34529],"iteration":563,"passed_time":3.039410632,"remaining_time":2.349615311},
{"learn":[65381.44988],"iteration":564,"passed_time":3.044364105,"remaining_time":2.343890948},
{"learn":[65372.85122],"iteration":565,"passed_time":3.050270892,"remaining_time":2.338900295},
{"learn":[65359.25171],"iteration":566,"passed_time":3.055624433,"remaining_time":2.333483915},
{"learn":[65347.23839],"iteration":567,"passed_time":3.061471631,"remaining_time":2.328443212},
{"learn":[65337.75459],"iteration":568,"passed_time":3.0675932,"remaining_time":2.323607503},
{"learn":[65332.70125],"iteration":569,"passed_time":3.072938643,"remaining_time":2.318181783},
{"learn":[65324.86064],"iteration":570,"passed_time":3.078381228,"remaining_time":2.312829329},
{"learn":[65317.84285],"iteration":571,"passed_time":3.08334658,"remaining_time":2.307119469},
{"learn":[65312.2517],"iteration":572,"passed_time":3.086863679,"remaining_time":2.300332969},
{"learn":[65299.18257],"iteration":573,"passed_time":3.091433749,"remaining_time":2.294339333},
{"learn":[65293.49782],"iteration":574,"passed_time":3.095472808,"remaining_time":2.287958162},
{"learn":[65288.46983],"iteration":575,"passed_time":3.100612973,"remaining_time":2.282395661},
{"learn":[65271.92378],"iteration":576,"passed_time":3.105376601,"remaining_time":2.276558583},
{"learn":[65265.58591],"iteration":577,"passed_time":3.109962386,"remaining_time":2.270595375},
{"learn":[65252.71198],"iteration":578,"passed_time":3.114988169,"remaining_time":2.264956855},
{"learn":[65232.60147],"iteration":579,"passed_time":3.120085813,"remaining_time":2.259372485},
{"learn":[65225.92474],"iteration":580,"passed_time":3.125209428,"remaining_time":2.25380852},
{"learn":[65214.75684],"iteration":581,"passed_time":3.130585877,"remaining_time":2.248427657},
{"learn":[65199.31332],"iteration":582,"passed_time":3.13524305,"remaining_time":2.242532336},
{"learn":[65193.85103],"iteration":583,"passed_time":3.139275606,"remaining_time":2.236196322},
{"learn":[65188.20937],"iteration":584,"passed_time":3.14485702,"remaining_time":2.230966946},
{"learn":[65184.33254],"iteration":585,"passed_time":3.15054788,"remaining_time":2.22581369},
{"learn":[65176.34011],"iteration":586,"passed_time":3.155397078,"remaining_time":2.220066428},
{"learn":[65167.64044],"iteration":587,"passed_time":3.159047551,"remaining_time":2.213482298},
{"learn":[65153.80654],"iteration":588,"passed_time":3.163062979,"remaining_time":2.207162792},
{"learn":[65144.78155],"iteration":589,"passed_time":3.167392844,"remaining_time":2.201069603},
{"learn":[65142.38477],"iteration":590,"passed_time":3.170966739,"remaining_time":2.194459215},
{"learn":[65131.89965],"iteration":591,"passed_time":3.175304802,"remaining_time":2.188385742},
{"learn":[65126.68505],"iteration":592,"passed_time":3.178768963,"remaining_time":2.181718327},
{"learn":[65122.72183],"iteration":593,"passed_time":3.183002539,"remaining_time":2.175587594},
{"learn":[65119.21656],"iteration":594,"passed_time":3.18705149,"remaining_time":2.169337569},
{"learn":[65111.90958],"iteration":595,"passed_time":3.191445583,"remaining_time":2.163328885},
{"learn":[65105.09483],"iteration":596,"passed_time":3.195643528,"remaining_time":2.157193202},
{"learn":[65099.56839],"iteration":597,"passed_time":3.217291732,"remaining_time":2.162794776},
{"learn":[65092.40172],"iteration":598,"passed_time":3.223842271,"remaining_time":2.158198248},
{"learn":[65084.34651],"iteration":599,"passed_time":3.230869017,"remaining_time":2.153912678},
{"learn":[65078.68163],"iteration":600,"passed_time":3.236532754,"remaining_time":2.148713093},
{"learn":[65067.13759],"iteration":601,"passed_time":3.242907061,"remaining_time":2.143981745},
{"learn":[65058.92021],"iteration":602,"passed_time":3.250757008,"remaining_time":2.140216471},
{"learn":[65053.43632],"iteration":603,"passed_time":3.259354213,"remaining_time":2.136927597},
{"learn":[65051.14056],"iteration":604,"passed_time":3.267129292,"remaining_time":2.133084413},
{"learn":[65044.78279],"iteration":605,"passed_time":3.276101913,"remaining_time":2.130006854},
{"learn":[65034.43311],"iteration":606,"passed_time":3.282634545,"remaining_time":2.125330109},
{"learn":[65023.8003],"iteration":607,"passed_time":3.289625635,"remaining_time":2.120942843},
{"learn":[65007.97354],"iteration":608,"passed_time":3.294981546,"remaining_time":2.115497183},
{"learn":[65003.7841],"iteration":609,"passed_time":3.301183238,"remaining_time":2.110592562},
{"learn":[64997.39779],"iteration":610,"passed_time":3.305938625,"remaining_time":2.104762889},
{"learn":[64990.57609],"iteration":611,"passed_time":3.310210765,"remaining_time":2.098630354},
{"learn":[64979.18862],"iteration":612,"passed_time":3.314029061,"remaining_time":2.092217368},
{"learn":[64966.62256],"iteration":613,"passed_time":3.317072858,"remaining_time":2.085325933},
{"learn":[64954.63281],"iteration":614,"passed_time":3.320496719,"remaining_time":2.078684938},
{"learn":[64942.3132],"iteration":615,"passed_time":3.323623051,"remaining_time":2.071868915},
{"learn":[64932.25055],"iteration":616,"passed_time":3.32730976,"remaining_time":2.065412704},
{"learn":[64927.0961],"iteration":617,"passed_time":3.330929999,"remaining_time":2.058924368},
{"learn":[64921.2127],"iteration":618,"passed_time":3.335038677,"remaining_time":2.052745939},
{"learn":[64913.59558],"iteration":619,"passed_time":3.339116972,"remaining_time":2.046555564},
{"learn":[64905.74869],"iteration":620,"passed_time":3.342548773,"remaining_time":2.039977432},
{"learn":[64902.27635],"iteration":621,"passed_time":3.345680219,"remaining_time":2.033226886},
{"learn":[64897.70681],"iteration":622,"passed_time":3.348580544,"remaining_time":2.026348098},
{"learn":[64889.84682],"iteration":623,"passed_time":3.352311866,"remaining_time":2.019982791},
{"learn":[64885.18125],"iteration":624,"passed_time":3.355144943,"remaining_time":2.013086966},
{"learn":[64879.49375],"iteration":625,"passed_time":3.358365037,"remaining_time":2.006435342},
{"learn":[64868.63136],"iteration":626,"passed_time":3.361258636,"remaining_time":1.999600432},
{"learn":[64853.71033],"iteration":627,"passed_time":3.364151206,"remaining_time":1.992777466},
{"learn":[64844.38008],"iteration":628,"passed_time":3.368290177,"remaining_time":1.986702155},
{"learn":[64833.57723],"iteration":629,"passed_time":3.37117486,"remaining_time":1.979896346},
{"learn":[64819.16907],"iteration":630,"passed_time":3.374059173,"remaining_time":1.973102749},
{"learn":[64815.00873],"iteration":631,"passed_time":3.376726307,"remaining_time":1.966195065},
{"learn":[64811.2402],"iteration":632,"passed_time":3.379211175,"remaining_time":1.959195104},
{"learn":[64804.04854],"iteration":633,"passed_time":3.381960903,"remaining_time":1.952362288},
{"learn":[64793.70238],"iteration":634,"passed_time":3.385067152,"remaining_time":1.945747261},
{"learn":[64780.4469],"iteration":635,"passed_time":3.388161995,"remaining_time":1.939136739},
{"learn":[64772.4722],"iteration":636,"passed_time":3.391163937,"remaining_time":1.932484316},
{"learn":[64767.59286],"iteration":637,"passed_time":3.394181549,"remaining_time":1.925852227},
{"learn":[64757.47021],"iteration":638,"passed_time":3.3971973,"remaining_time":1.9192304},
{"learn":[64751.85848],"iteration":639,"passed_time":3.400471864,"remaining_time":1.912765423},
{"learn":[64743.04187],"iteration":640,"passed_time":3.403627503,"remaining_time":1.906243796},
{"learn":[64733.60087],"iteration":641,"passed_time":3.406644535,"remaining_time":1.899655364},
{"learn":[64727.97115],"iteration":642,"passed_time":3.409621645,"remaining_time":1.893055874},
{"learn":[64712.80976],"iteration":643,"passed_time":3.412870422,"remaining_time":1.886617811},
{"learn":[64697.06279],"iteration":644,"passed_time":3.415748474,"remaining_time":1.879985594},
{"learn":[64686.91329],"iteration":645,"passed_time":3.419507036,"remaining_time":1.873847509},
{"learn":[64676.93906],"iteration":646,"passed_time":3.422398544,"remaining_time":1.867243719},
{"learn":[64667.02063],"iteration":647,"passed_time":3.425149006,"remaining_time":1.860574769},
{"learn":[64656.15074],"iteration":648,"passed_time":3.42777261,"remaining_time":1.853849285},
{"learn":[64645.58709],"iteration":649,"passed_time":3.430707875,"remaining_time":1.84730424},
{"learn":[64635.62758],"iteration":650,"passed_time":3.434778262,"remaining_time":1.841378822},
{"learn":[64629.2641],"iteration":651,"passed_time":3.437550601,"remaining_time":1.834766271},
{"learn":[64626.12208],"iteration":652,"passed_time":3.440198815,"remaining_time":1.828099523},
{"learn":[64623.01771],"iteration":653,"passed_time":3.443043593,"remaining_time":1.821549057},
{"learn":[64618.77669],"iteration":654,"passed_time":3.445847119,"remaining_time":1.814988177},
{"learn":[64615.12955],"iteration":655,"passed_time":3.448772899,"remaining_time":1.808502862},
{"learn":[64609.84717],"iteration":656,"passed_time":3.451796383,"remaining_time":1.80207939},
{"learn":[64599.14386],"iteration":657,"passed_time":3.454534122,"remaining_time":1.795517735},
{"learn":[64592.32142],"iteration":658,"passed_time":3.457284258,"remaining_time":1.7889741},
{"learn":[64584.3713],"iteration":659,"passed_time":3.459969977,"remaining_time":1.782408776},
{"learn":[64574.74952],"iteration":660,"passed_time":3.463023022,"remaining_time":1.776043577},
{"learn":[64568.21166],"iteration":661,"passed_time":3.465817598,"remaining_time":1.769556417},
{"learn":[64559.37085],"iteration":662,"passed_time":3.46856461,"remaining_time":1.763056219},
{"learn":[64555.41408],"iteration":663,"passed_time":3.471238718,"remaining_time":1.756530436},
{"learn":[64551.69231],"iteration":664,"passed_time":3.478256783,"remaining_time":1.752204545},
{"learn":[64537.51974],"iteration":665,"passed_time":3.481693099,"remaining_time":1.746074317},
{"learn":[64531.5796],"iteration":666,"passed_time":3.484850727,"remaining_time":1.739813032},
{"learn":[64519.46913],"iteration":667,"passed_time":3.493057455,"remaining_time":1.736070471},
{"learn":[64510.67889],"iteration":668,"passed_time":3.496599551,"remaining_time":1.730006654},
{"learn":[64504.18492],"iteration":669,"passed_time":3.499789884,"remaining_time":1.723777107},
{"learn":[64493.54919],"iteration":670,"passed_time":3.502902931,"remaining_time":1.717518725},
{"learn":[64485.49331],"iteration":671,"passed_time":3.505964856,"remaining_time":1.711244751},
{"learn":[64482.14601],"iteration":672,"passed_time":3.508713672,"remaining_time":1.704828188},
{"learn":[64477.26606],"iteration":673,"passed_time":3.511297527,"remaining_time":1.698342721},
{"learn":[64466.3614],"iteration":674,"passed_time":3.514220336,"remaining_time":1.692032014},
{"learn":[64461.18974],"iteration":675,"passed_time":3.517069481,"remaining_time":1.685696024},
{"learn":[64453.16446],"iteration":676,"passed_time":3.521387544,"remaining_time":1.680071162},
{"learn":[64435.1741],"iteration":677,"passed_time":3.53885676,"remaining_time":1.680695983},
{"learn":[64419.75326],"iteration":678,"passed_time":3.551550805,"remaining_time":1.679010027},
{"learn":[64410.69503],"iteration":679,"passed_time":3.555908483,"remaining_time":1.673368698},
{"learn":[64409.00727],"iteration":680,"passed_time":3.559678778,"remaining_time":1.667455992},
{"learn":[64403.01246],"iteration":681,"passed_time":3.563574131,"remaining_time":1.661607879},
{"learn":[64396.2378],"iteration":682,"passed_time":3.567146076,"remaining_time":1.655615382},
{"learn":[64389.50112],"iteration":683,"passed_time":3.570501541,"remaining_time":1.649529952},
{"learn":[64377.80442],"iteration":684,"passed_time":3.573352906,"remaining_time":1.643220679},
{"learn":[64370.53387],"iteration":685,"passed_time":3.576650305,"remaining_time":1.63712565},
{"learn":[64364.73991],"iteration":686,"passed_time":3.579292383,"remaining_time":1.630740198},
{"learn":[64355.19728],"iteration":687,"passed_time":3.582117121,"remaining_time":1.624448462},
{"learn":[64347.432],"iteration":688,"passed_time":3.585055242,"remaining_time":1.618217968},
{"learn":[64341.5576],"iteration":689,"passed_time":3.587698076,"remaining_time":1.611864353},
{"learn":[64333.54933],"iteration":690,"passed_time":3.590640496,"remaining_time":1.605655446},
{"learn":[64330.52948],"iteration":691,"passed_time":3.59297744,"remaining_time":1.599186491},
{"learn":[64321.5297],"iteration":692,"passed_time":3.59605492,"remaining_time":1.593057519},
{"learn":[64310.51776],"iteration":693,"passed_time":3.610563424,"remaining_time":1.591977533},
{"learn":[64305.83232],"iteration":694,"passed_time":3.615842762,"remaining_time":1.586808694},
{"learn":[64301.57949],"iteration":695,"passed_time":3.620835633,"remaining_time":1.581514414},
{"learn":[64292.57865],"iteration":696,"passed_time":3.643122725,"remaining_time":1.583739147},
{"learn":[64288.76054],"iteration":697,"passed_time":3.648668902,"remaining_time":1.578650442},
{"learn":[64281.17959],"iteration":698,"passed_time":3.654637579,"remaining_time":1.573742362},
{"learn":[64271.70163],"iteration":699,"passed_time":3.662332061,"remaining_time":1.569570883},
{"learn":[64267.51386],"iteration":700,"passed_time":3.667560377,"remaining_time":1.56433745},
{"learn":[64265.39217],"iteration":701,"passed_time":3.673711204,"remaining_time":1.559495639},
{"learn":[64257.55179],"iteration":702,"passed_time":3.680163744,"remaining_time":1.554777571},
{"learn":[64250.98588],"iteration":703,"passed_time":3.688192717,"remaining_time":1.550717392},
{"learn":[64243.01165],"iteration":704,"passed_time":3.693606466,"remaining_time":1.545551642},
{"learn":[64229.80413],"iteration":705,"passed_time":3.698493304,"remaining_time":1.540165767},
{"learn":[64220.84366],"iteration":706,"passed_time":3.704356027,"remaining_time":1.535185737},
{"learn":[64208.44957],"iteration":707,"passed_time":3.710133976,"remaining_time":1.53016825},
{"learn":[64201.7307],"iteration":708,"passed_time":3.714545435,"remaining_time":1.524587759},
{"learn":[64194.68527],"iteration":709,"passed_time":3.730648855,"remaining_time":1.523786152},
{"learn":[64191.08337],"iteration":710,"passed_time":3.734520262,"remaining_time":1.517969558},
{"learn":[64183.70734],"iteration":711,"passed_time":3.738317287,"remaining_time":1.512128341},
{"learn":[64175.14677],"iteration":712,"passed_time":3.741498829,"remaining_time":1.506045111},
{"learn":[64168.43405],"iteration":713,"passed_time":3.745161062,"remaining_time":1.500162554},
{"learn":[64156.4045],"iteration":714,"passed_time":3.747953885,"remaining_time":1.49393966},
{"learn":[64152.9453],"iteration":715,"passed_time":3.750842738,"remaining_time":1.487764438},
{"learn":[64148.02396],"iteration":716,"passed_time":3.753597763,"remaining_time":1.48154556},
{"learn":[64144.47736],"iteration":717,"passed_time":3.756360913,"remaining_time":1.475339523},
{"learn":[64138.98831],"iteration":718,"passed_time":3.759790044,"remaining_time":1.469403341},
{"learn":[64132.49774],"iteration":719,"passed_time":3.762601667,"remaining_time":1.463233982},
{"learn":[64127.28163],"iteration":720,"passed_time":3.766022144,"remaining_time":1.45730954},
{"learn":[64118.35139],"iteration":721,"passed_time":3.769491486,"remaining_time":1.451410849},
{"learn":[64114.66651],"iteration":722,"passed_time":3.772984459,"remaining_time":1.445527933},
{"learn":[64105.46507],"iteration":723,"passed_time":3.776266628,"remaining_time":1.439571256},
{"learn":[64094.16185],"iteration":724,"passed_time":3.779038513,"remaining_time":1.433428401},
{"learn":[64087.28515],"iteration":725,"passed_time":3.782173588,"remaining_time":1.427431905},
{"learn":[64082.63202],"iteration":726,"passed_time":3.787915515,"remaining_time":1.422422195},
{"learn":[64075.01968],"iteration":727,"passed_time":3.791158984,"remaining_time":1.416476983},
{"learn":[64062.39157],"iteration":728,"passed_time":3.795103375,"remaining_time":1.410799746},
{"learn":[64053.21568],"iteration":729,"passed_time":3.798624754,"remaining_time":1.404970799},
{"learn":[64046.81801],"iteration":730,"passed_time":3.802480349,"remaining_time":1.399271155},
{"learn":[64040.93678],"iteration":731,"passed_time":3.805689303,"remaining_time":1.393339799},
{"learn":[64037.4651],"iteration":732,"passed_time":3.808992967,"remaining_time":1.387450372},
{"learn":[64034.53873],"iteration":733,"passed_time":3.812072605,"remaining_time":1.381486802},
{"learn":[64018.16646],"iteration":734,"passed_time":3.815169075,"remaining_time":1.37553715},
{"learn":[64012.44701],"iteration":735,"passed_time":3.818560056,"remaining_time":1.36970089},
{"learn":[64004.61823],"iteration":736,"passed_time":3.821629928,"remaining_time":1.363756677},
{"learn":[63999.62572],"iteration":737,"passed_time":3.825072454,"remaining_time":1.357952551},
{"learn":[63994.96871],"iteration":738,"passed_time":3.828129838,"remaining_time":1.352018793},
{"learn":[63988.34582],"iteration":739,"passed_time":3.831913569,"remaining_time":1.346348011},
{"learn":[63978.28091],"iteration":740,"passed_time":3.835276139,"remaining_time":1.340535115},
{"learn":[63969.26126],"iteration":741,"passed_time":3.838509522,"remaining_time":1.334683904},
{"learn":[63955.4119],"iteration":742,"passed_time":3.841764617,"remaining_time":1.32884725},
{"learn":[63947.20821],"iteration":743,"passed_time":3.846070411,"remaining_time":1.323379066},
{"learn":[63939.43143],"iteration":744,"passed_time":3.849894825,"remaining_time":1.317749235},
{"learn":[63931.62054],"iteration":745,"passed_time":3.852906641,"remaining_time":1.311847569},
{"learn":[63918.56459],"iteration":746,"passed_time":3.856049012,"remaining_time":1.305997858},
{"learn":[63911.26883],"iteration":747,"passed_time":3.859326709,"remaining_time":1.300200977},
{"learn":[63908.88643],"iteration":748,"passed_time":3.862410456,"remaining_time":1.294345827},
{"learn":[63896.17573],"iteration":749,"passed_time":3.87423647,"remaining_time":1.291412157},
{"learn":[63887.31895],"iteration":750,"passed_time":3.877019854,"remaining_time":1.285456649},
{"learn":[63879.17161],"iteration":751,"passed_time":3.88104634,"remaining_time":1.279919538},
{"learn":[63874.78204],"iteration":752,"passed_time":3.884467355,"remaining_time":1.274187831},
{"learn":[63874.71543],"iteration":753,"passed_time":3.888094954,"remaining_time":1.268529653},
{"learn":[63869.42818],"iteration":754,"passed_time":3.890723141,"remaining_time":1.262552543},
{"learn":[63860.1058],"iteration":755,"passed_time":3.893436968,"remaining_time":1.256611931},
{"learn":[63852.0094],"iteration":756,"passed_time":3.895829802,"remaining_time":1.250576806},
{"learn":[63850.30165],"iteration":757,"passed_time":3.898788275,"remaining_time":1.244731877},
{"learn":[63843.93761],"iteration":758,"passed_time":3.901750395,"remaining_time":1.238895712},
{"learn":[63842.79834],"iteration":759,"passed_time":3.904463008,"remaining_time":1.232988318},
{"learn":[63827.72288],"iteration":760,"passed_time":3.917911727,"remaining_time":1.230461108},
{"learn":[63821.96537],"iteration":761,"passed_time":3.92039959,"remaining_time":1.224481762},
{"learn":[63816.94695],"iteration":762,"passed_time":3.922767789,"remaining_time":1.218474398},
{"learn":[63810.73404],"iteration":763,"passed_time":3.924978812,"remaining_time":1.21242801},
{"learn":[63800.62811],"iteration":764,"passed_time":3.927590019,"remaining_time":1.206514581},
{"learn":[63790.93866],"iteration":765,"passed_time":3.929912143,"remaining_time":1.200521464},
{"learn":[63785.84568],"iteration":766,"passed_time":3.934190367,"remaining_time":1.195132145},
{"learn":[63784.57074],"iteration":767,"passed_time":3.937054816,"remaining_time":1.189318642},
{"learn":[63777.68359],"iteration":768,"passed_time":3.939514806,"remaining_time":1.183391314},
{"learn":[63771.92225],"iteration":769,"passed_time":3.942277007,"remaining_time":1.177563262},
{"learn":[63765.16946],"iteration":770,"passed_time":3.944802767,"remaining_time":1.171672936},
{"learn":[63756.49926],"iteration":771,"passed_time":3.948559882,"remaining_time":1.166154991},
{"learn":[63746.68055],"iteration":772,"passed_time":3.952139224,"remaining_time":1.160589397},
{"learn":[63742.58278],"iteration":773,"passed_time":3.955392854,"remaining_time":1.154933831},
{"learn":[63740.67303],"iteration":774,"passed_time":3.95836453,"remaining_time":1.149202605},
{"learn":[63737.96943],"iteration":775,"passed_time":3.961323344,"remaining_time":1.14347478},
{"learn":[63730.28084],"iteration":776,"passed_time":3.964413984,"remaining_time":1.137791916},
{"learn":[63730.2167],"iteration":777,"passed_time":3.9672068,"remaining_time":1.132030732},
{"learn":[63716.38017],"iteration":778,"passed_time":3.970560002,"remaining_time":1.12643615},
{"learn":[63708.45387],"iteration":779,"passed_time":3.97316524,"remaining_time":1.12063635},
{"learn":[63700.76597],"iteration":780,"passed_time":3.975428081,"remaining_time":1.114748719},
{"learn":[63688.44021],"iteration":781,"passed_time":3.978026692,"remaining_time":1.108963963},
{"learn":[63684.22036],"iteration":782,"passed_time":3.980718972,"remaining_time":1.103213304},
{"learn":[63680.55169],"iteration":783,"passed_time":3.982806733,"remaining_time":1.097303896},
{"learn":[63678.50642],"iteration":784,"passed_time":3.985315592,"remaining_time":1.091519557},
{"learn":[63676.89038],"iteration":785,"passed_time":3.987894421,"remaining_time":1.085762603},
{"learn":[63663.89622],"iteration":786,"passed_time":3.990325422,"remaining_time":1.079973716},
{"learn":[63658.77621],"iteration":787,"passed_time":3.992919191,"remaining_time":1.074237143},
{"learn":[63652.21383],"iteration":788,"passed_time":3.995288776,"remaining_time":1.068448583},
{"learn":[63643.39037],"iteration":789,"passed_time":3.998937675,"remaining_time":1.063008749},
{"learn":[63640.19596],"iteration":790,"passed_time":4.002388847,"remaining_time":1.0575212},
{"learn":[63634.15215],"iteration":791,"passed_time":4.005721156,"remaining_time":1.052007576},
{"learn":[63634.08049],"iteration":792,"passed_time":4.008337165,"remaining_time":1.046312476},
{"learn":[63627.65674],"iteration":793,"passed_time":4.01170829,"remaining_time":1.040821043},
{"learn":[63615.8903],"iteration":794,"passed_time":4.014184897,"remaining_time":1.035104282},
{"learn":[63608.50987],"iteration":795,"passed_time":4.01674472,"remaining_time":1.029416989},
{"learn":[63599.17338],"iteration":796,"passed_time":4.019457013,"remaining_time":1.023776379},
{"learn":[63591.17299],"iteration":797,"passed_time":4.022095687,"remaining_time":1.018124472},
{"learn":[63583.00512],"iteration":798,"passed_time":4.024723068,"remaining_time":1.012477268},
{"learn":[63580.11087],"iteration":799,"passed_time":4.027052408,"remaining_time":1.006763102},
{"learn":[63574.73334],"iteration":800,"passed_time":4.029479893,"remaining_time":1.001081771},
{"learn":[63569.50603],"iteration":801,"passed_time":4.031844655,"remaining_time":0.9953930695},
{"learn":[63554.7788],"iteration":802,"passed_time":4.034412845,"remaining_time":0.9897625534},
{"learn":[63543.60786],"iteration":803,"passed_time":4.036917604,"remaining_time":0.984124192},
{"learn":[63538.43584],"iteration":804,"passed_time":4.039277307,"remaining_time":0.978458478},
{"learn":[63532.96812],"iteration":805,"passed_time":4.042149373,"remaining_time":0.9729242908},
{"learn":[63523.43185],"iteration":806,"passed_time":4.044756282,"remaining_time":0.9673332868},
{"learn":[63520.86148],"iteration":807,"passed_time":4.047396198,"remaining_time":0.9617575124},
{"learn":[63509.36304],"iteration":808,"passed_time":4.050200091,"remaining_time":0.95622771},
{"learn":[63499.49219],"iteration":809,"passed_time":4.053076115,"remaining_time":0.9507215578},
{"learn":[63492.99648],"iteration":810,"passed_time":4.055951309,"remaining_time":0.9452216984},
{"learn":[63489.06571],"iteration":811,"passed_time":4.059085,"remaining_time":0.9397881527},
{"learn":[63483.33885],"iteration":812,"passed_time":4.062077711,"remaining_time":0.9343278376},
{"learn":[63478.64571],"iteration":813,"passed_time":4.06453691,"remaining_time":0.9287516772},
{"learn":[63474.80349],"iteration":814,"passed_time":4.067236108,"remaining_time":0.9232376441},
{"learn":[63468.06622],"iteration":815,"passed_time":4.070016515,"remaining_time":0.9177488219},
{"learn":[63461.44055],"iteration":816,"passed_time":4.07273284,"remaining_time":0.9122522762},
{"learn":[63449.68342],"iteration":817,"passed_time":4.075794417,"remaining_time":0.9068393447},
{"learn":[63441.10547],"iteration":818,"passed_time":4.078949668,"remaining_time":0.9014528571},
{"learn":[63438.4483],"iteration":819,"passed_time":4.082064518,"remaining_time":0.8960629431},
{"learn":[63428.04435],"iteration":820,"passed_time":4.085149843,"remaining_time":0.8906721339},
{"learn":[63410.71008],"iteration":821,"passed_time":4.088399709,"remaining_time":0.8853225646},
{"learn":[63408.18427],"iteration":822,"passed_time":4.091280054,"remaining_time":0.8798986265},
{"learn":[63391.61101],"iteration":823,"passed_time":4.094306827,"remaining_time":0.8745121377},
{"learn":[63383.82094],"iteration":824,"passed_time":4.097596805,"remaining_time":0.869187201},
{"learn":[63376.05021],"iteration":825,"passed_time":4.100786317,"remaining_time":0.8638460281},
{"learn":[63367.32155],"iteration":826,"passed_time":4.121899898,"remaining_time":0.8622595918},
{"learn":[63363.00867],"iteration":827,"passed_time":4.127425835,"remaining_time":0.8573879754},
{"learn":[63356.9043],"iteration":828,"passed_time":4.134195745,"remaining_time":0.8527713781},
{"learn":[63351.31343],"iteration":829,"passed_time":4.139741507,"remaining_time":0.8478988629},
{"learn":[63346.69305],"iteration":830,"passed_time":4.145673308,"remaining_time":0.8431032359},
{"learn":[63338.16608],"iteration":831,"passed_time":4.152651168,"remaining_time":0.8385161011},
{"learn":[63329.38633],"iteration":832,"passed_time":4.157902468,"remaining_time":0.8335770854},
{"learn":[63324.63706],"iteration":833,"passed_time":4.16393554,"remaining_time":0.8287929252},
{"learn":[63316.94246],"iteration":834,"passed_time":4.170005651,"remaining_time":0.8240130927},
{"learn":[63309.29375],"iteration":835,"passed_time":4.174780661,"remaining_time":0.8189761106},
{"learn":[63303.67855],"iteration":836,"passed_time":4.18099935,"remaining_time":0.8142209009},
{"learn":[63291.74368],"iteration":837,"passed_time":4.186062873,"remaining_time":0.8092388847},
{"learn":[63284.51049],"iteration":838,"passed_time":4.191180339,"remaining_time":0.8042670257},
{"learn":[63279.18973],"iteration":839,"passed_time":4.196354258,"remaining_time":0.7993055729},
{"learn":[63275.32495],"iteration":840,"passed_time":4.201332073,"remaining_time":0.7943065394},
{"learn":[63265.16022],"iteration":841,"passed_time":4.207454175,"remaining_time":0.7895222798},
{"learn":[63251.61563],"iteration":842,"passed_time":4.212202523,"remaining_time":0.784478999},
{"learn":[63245.31159],"iteration":843,"passed_time":4.216958338,"remaining_time":0.779437797},
{"learn":[63238.20802],"iteration":844,"passed_time":4.221360794,"remaining_time":0.7743324533},
{"learn":[63232.79738],"iteration":845,"passed_time":4.237802328,"remaining_time":0.7714202819},
{"learn":[63224.80157],"iteration":846,"passed_time":4.244133985,"remaining_time":0.7666499406},
{"learn":[63220.97974],"iteration":847,"passed_time":4.251705226,"remaining_time":0.7620981066},
{"learn":[63211.88472],"iteration":848,"passed_time":4.269828087,"remaining_time":0.7594158318},
{"learn":[63207.72242],"iteration":849,"passed_time":4.275690632,"remaining_time":0.7545336409},
{"learn":[63203.99161],"iteration":850,"passed_time":4.282307744,"remaining_time":0.7497812619},
{"learn":[63198.44506],"iteration":851,"passed_time":4.287818422,"remaining_time":0.744832308},
{"learn":[63184.27277],"iteration":852,"passed_time":4.293706806,"remaining_time":0.7399471283},
{"learn":[63179.66181],"iteration":853,"passed_time":4.300657041,"remaining_time":0.7352411334},
{"learn":[63172.31949],"iteration":854,"passed_time":4.305920922,"remaining_time":0.7302438991},
{"learn":[63162.36123],"iteration":855,"passed_time":4.312166365,"remaining_time":0.7254111642},
{"learn":[63156.2809],"iteration":856,"passed_time":4.317611257,"remaining_time":0.7204415516},
{"learn":[63143.7022],"iteration":857,"passed_time":4.322566459,"remaining_time":0.715389787},
{"learn":[63136.98131],"iteration":858,"passed_time":4.327971382,"remaining_time":0.7104120662},
{"learn":[63126.03212],"iteration":859,"passed_time":4.345008745,"remaining_time":0.707327005},
{"learn":[63124.39615],"iteration":860,"passed_time":4.350953946,"remaining_time":0.7024188135},
{"learn":[63122.0898],"iteration":861,"passed_time":4.357131134,"remaining_time":0.6975453555},
{"learn":[63118.87453],"iteration":862,"passed_time":4.393119122,"remaining_time":0.6974012975},
{"learn":[63111.94576],"iteration":863,"passed_time":4.399234346,"remaining_time":0.692472073},
{"learn":[63100.63221],"iteration":864,"passed_time":4.40695053,"remaining_time":0.6877899672},
{"learn":[63091.06361],"iteration":865,"passed_time":4.413905627,"remaining_time":0.6829830877},
{"learn":[63082.05585],"iteration":866,"passed_time":4.423106119,"remaining_time":0.6785157023},
{"learn":[63077.65687],"iteration":867,"passed_time":4.429305542,"remaining_time":0.6735810271},
{"learn":[63068.65709],"iteration":868,"passed_time":4.451426435,"remaining_time":0.6710435708},
{"learn":[63057.00529],"iteration":869,"passed_time":4.457877197,"remaining_time":0.6661195811},
{"learn":[63039.43246],"iteration":870,"passed_time":4.465292056,"remaining_time":0.661334874},
{"learn":[63033.09664],"iteration":871,"passed_time":4.47151,"remaining_time":0.6563684404},
{"learn":[63023.75194],"iteration":872,"passed_time":4.478126676,"remaining_time":0.6514571454},
{"learn":[63014.01861],"iteration":873,"passed_time":4.48374504,"remaining_time":0.6463980263},
{"learn":[63006.32254],"iteration":874,"passed_time":4.489225302,"remaining_time":0.6413179003},
{"learn":[62991.98142],"iteration":875,"passed_time":4.496081748,"remaining_time":0.6364316629},
{"learn":[62982.18672],"iteration":876,"passed_time":4.502783086,"remaining_time":0.6315191785},
{"learn":[62974.90953],"iteration":877,"passed_time":4.509576183,"remaining_time":0.6266153694},
{"learn":[62967.21052],"iteration":878,"passed_time":4.515589369,"remaining_time":0.6215999017},
{"learn":[62961.58016],"iteration":879,"passed_time":4.520756998,"remaining_time":0.6164668634},
{"learn":[62957.40091],"iteration":880,"passed_time":4.541804272,"remaining_time":0.6134786701},
{"learn":[62946.1303],"iteration":881,"passed_time":4.547287427,"remaining_time":0.6083672522},
{"learn":[62939.74967],"iteration":882,"passed_time":4.553189144,"remaining_time":0.6033104528},
{"learn":[62929.23717],"iteration":883,"passed_time":4.558698525,"remaining_time":0.598200259},
{"learn":[62918.89277],"iteration":884,"passed_time":4.564563418,"remaining_time":0.5931353594},
{"learn":[62910.2138],"iteration":885,"passed_time":4.571786351,"remaining_time":0.5882433906},
{"learn":[62905.11415],"iteration":886,"passed_time":4.578457009,"remaining_time":0.5832758084},
{"learn":[62897.06153],"iteration":887,"passed_time":4.584643796,"remaining_time":0.5782433616},
{"learn":[62890.92108],"iteration":888,"passed_time":4.591097025,"remaining_time":0.5732415858},
{"learn":[62888.92041],"iteration":889,"passed_time":4.596180287,"remaining_time":0.5680672265},
{"learn":[62878.98793],"iteration":890,"passed_time":4.602132732,"remaining_time":0.5629994027},
{"learn":[62871.54524],"iteration":891,"passed_time":4.606703396,"remaining_time":0.5577622946},
{"learn":[62866.75858],"iteration":892,"passed_time":4.612870187,"remaining_time":0.5527179284},
{"learn":[62863.48059],"iteration":893,"passed_time":4.616973703,"remaining_time":0.5474264122},
{"learn":[62853.23135],"iteration":894,"passed_time":4.621902047,"remaining_time":0.5422343184},
{"learn":[62850.94221],"iteration":895,"passed_time":4.626911686,"remaining_time":0.5370522492},
{"learn":[62844.27187],"iteration":896,"passed_time":4.631454575,"remaining_time":0.531816969},
{"learn":[62836.56072],"iteration":897,"passed_time":4.636239442,"remaining_time":0.5266107161},
{"learn":[62828.89094],"iteration":898,"passed_time":4.640683077,"remaining_time":0.5213670643},
{"learn":[62826.7999],"iteration":899,"passed_time":4.645413738,"remaining_time":0.516157082},
{"learn":[62819.09419],"iteration":900,"passed_time":4.65040902,"remaining_time":0.5109772397},
{"learn":[62807.97089],"iteration":901,"passed_time":4.654654883,"remaining_time":0.5057163842},
{"learn":[62807.87729],"iteration":902,"passed_time":4.657605775,"remaining_time":0.5003186713},
{"learn":[62800.57226],"iteration":903,"passed_time":4.661795068,"remaining_time":0.4950578834},
{"learn":[62793.02677],"iteration":904,"passed_time":4.665892589,"remaining_time":0.4897898297},
{"learn":[62789.95839],"iteration":905,"passed_time":4.669673354,"remaining_time":0.4844914959},
{"learn":[62788.17695],"iteration":906,"passed_time":4.673137249,"remaining_time":0.4791640178},
{"learn":[62776.62909],"iteration":907,"passed_time":4.677222109,"remaining_time":0.4739035617},
{"learn":[62773.36957],"iteration":908,"passed_time":4.680375815,"remaining_time":0.4685524743},
{"learn":[62762.04266],"iteration":909,"passed_time":4.683922546,"remaining_time":0.463245087},
{"learn":[62749.66255],"iteration":910,"passed_time":4.687539631,"remaining_time":0.4579484381},
{"learn":[62747.48138],"iteration":911,"passed_time":4.690836677,"remaining_time":0.4526245916},
{"learn":[62743.98725],"iteration":912,"passed_time":4.69484057,"remaining_time":0.4473725406},
{"learn":[62735.62975],"iteration":913,"passed_time":4.698423179,"remaining_time":0.4420835814},
{"learn":[62735.46742],"iteration":914,"passed_time":4.701394996,"remaining_time":0.4367416117},
{"learn":[62732.77773],"iteration":915,"passed_time":4.704478527,"remaining_time":0.4314150614},
{"learn":[62728.96723],"iteration":916,"passed_time":4.707834586,"remaining_time":0.4261180705},
{"learn":[62726.11667],"iteration":917,"passed_time":4.711417172,"remaining_time":0.4208455426},
{"learn":[62723.48454],"iteration":918,"passed_time":4.714394597,"remaining_time":0.415523354},
{"learn":[62719.32242],"iteration":919,"passed_time":4.717403969,"remaining_time":0.4102090408},
{"learn":[62708.74203],"iteration":920,"passed_time":4.72024413,"remaining_time":0.4048852185},
{"learn":[62701.33574],"iteration":921,"passed_time":4.723246483,"remaining_time":0.3995805051},
{"learn":[62694.06521],"iteration":922,"passed_time":4.725853736,"remaining_time":0.3942478198},
{"learn":[62685.50196],"iteration":923,"passed_time":4.728888205,"remaining_time":0.3889561727},
{"learn":[62682.95379],"iteration":924,"passed_time":4.731941011,"remaining_time":0.3836708928},
{"learn":[62674.75611],"iteration":925,"passed_time":4.735030082,"remaining_time":0.3783933327},
{"learn":[62667.43035],"iteration":926,"passed_time":4.738349868,"remaining_time":0.3731386627},
{"learn":[62662.67886],"iteration":927,"passed_time":4.741520009,"remaining_time":0.3678765524},
{"learn":[62656.28422],"iteration":928,"passed_time":4.744670909,"remaining_time":0.3626174752},
{"learn":[62655.47743],"iteration":929,"passed_time":4.747226439,"remaining_time":0.3573181191},
{"learn":[62649.10335],"iteration":930,"passed_time":4.750027801,"remaining_time":0.3520428768},
{"learn":[62644.20595],"iteration":931,"passed_time":4.753252866,"remaining_time":0.3468038572},
{"learn":[62644.11462],"iteration":932,"passed_time":4.756229742,"remaining_time":0.341551332},
{"learn":[62637.47263],"iteration":933,"passed_time":4.760122894,"remaining_time":0.3363684272},
{"learn":[62634.42997],"iteration":934,"passed_time":4.76304135,"remaining_time":0.3311205216},
{"learn":[62634.30655],"iteration":935,"passed_time":4.765808214,"remaining_time":0.3258672283},
{"learn":[62625.10858],"iteration":936,"passed_time":4.768940778,"remaining_time":0.3206438303},
{"learn":[62620.31044],"iteration":937,"passed_time":4.772512522,"remaining_time":0.3154539194},
{"learn":[62615.34317],"iteration":938,"passed_time":4.77575442,"remaining_time":0.3102460273},
{"learn":[62610.4871],"iteration":939,"passed_time":4.779363951,"remaining_time":0.3050657841},
{"learn":[62599.42454],"iteration":940,"passed_time":4.782684708,"remaining_time":0.2998707734},
{"learn":[62593.07243],"iteration":941,"passed_time":4.785966932,"remaining_time":0.2946773695},
{"learn":[62589.51291],"iteration":942,"passed_time":4.789495445,"remaining_time":0.289502906},
{"learn":[62581.97829],"iteration":943,"passed_time":4.793121735,"remaining_time":0.28433773},
{"learn":[62577.7868],"iteration":944,"passed_time":4.79625199,"remaining_time":0.2791469412},
{"learn":[62577.09146],"iteration":945,"passed_time":4.79942221,"remaining_time":0.27396279},
{"learn":[62568.74632],"iteration":946,"passed_time":4.80288027,"remaining_time":0.2687990014},
{"learn":[62558.86847],"iteration":947,"passed_time":4.806448855,"remaining_time":0.2636448739},
{"learn":[62554.92786],"iteration":948,"passed_time":4.809465589,"remaining_time":0.258464431},
{"learn":[62546.45465],"iteration":949,"passed_time":4.813536925,"remaining_time":0.2533440487},
{"learn":[62536.43907],"iteration":950,"passed_time":4.816771883,"remaining_time":0.2481827784},
{"learn":[62529.19227],"iteration":951,"passed_time":4.820642275,"remaining_time":0.2430575937},
{"learn":[62529.06305],"iteration":952,"passed_time":4.823056352,"remaining_time":0.2378632199},
{"learn":[62521.85004],"iteration":953,"passed_time":4.826557921,"remaining_time":0.2327271115},
{"learn":[62518.38305],"iteration":954,"passed_time":4.830555083,"remaining_time":0.2276177788},
{"learn":[62518.10472],"iteration":955,"passed_time":4.834252181,"remaining_time":0.2224969623},
{"learn":[62508.74215],"iteration":956,"passed_time":4.838419905,"remaining_time":0.2174002674},
{"learn":[62508.6148],"iteration":957,"passed_time":4.842373943,"remaining_time":0.2122961436},
{"learn":[62506.12412],"iteration":958,"passed_time":4.847024294,"remaining_time":0.2072241877},
{"learn":[62501.89865],"iteration":959,"passed_time":4.850893561,"remaining_time":0.2021205651},
{"learn":[62496.72436],"iteration":960,"passed_time":4.854628172,"remaining_time":0.1970140465},
{"learn":[62487.88801],"iteration":961,"passed_time":4.85794575,"remaining_time":0.1918939069},
{"learn":[62475.12318],"iteration":962,"passed_time":4.866468443,"remaining_time":0.1869774999},
{"learn":[62469.12677],"iteration":963,"passed_time":4.871920249,"remaining_time":0.1819389305},
{"learn":[62460.09459],"iteration":964,"passed_time":4.87631184,"remaining_time":0.1768610512},
{"learn":[62454.01532],"iteration":965,"passed_time":4.880845341,"remaining_time":0.1717895876},
{"learn":[62446.01047],"iteration":966,"passed_time":4.885846664,"remaining_time":0.1667352016},
{"learn":[62445.9167],"iteration":967,"passed_time":4.889746664,"remaining_time":0.1616445178},
{"learn":[62435.35715],"iteration":968,"passed_time":4.894049883,"remaining_time":0.1565691913},
{"learn":[62427.13435],"iteration":969,"passed_time":4.897442059,"remaining_time":0.1514672802},
{"learn":[62422.65652],"iteration":970,"passed_time":4.902098236,"remaining_time":0.1464066414},
{"learn":[62414.72644],"iteration":971,"passed_time":4.906511818,"remaining_time":0.1413398466},
{"learn":[62410.67902],"iteration":972,"passed_time":4.91040272,"remaining_time":0.1362598905},
{"learn":[62401.79497],"iteration":973,"passed_time":4.915336549,"remaining_time":0.1312102159},
{"learn":[62398.17307],"iteration":974,"passed_time":4.920279533,"remaining_time":0.1261610137},
{"learn":[62395.45484],"iteration":975,"passed_time":4.925001411,"remaining_time":0.1211065921},
{"learn":[62389.12808],"iteration":976,"passed_time":4.930067916,"remaining_time":0.1160609643},
{"learn":[62378.87134],"iteration":977,"passed_time":4.934587027,"remaining_time":0.1110029802},
{"learn":[62375.63342],"iteration":978,"passed_time":4.939610728,"remaining_time":0.1059569206},
{"learn":[62366.5457],"iteration":979,"passed_time":4.961484191,"remaining_time":0.1012547794},
{"learn":[62361.05042],"iteration":980,"passed_time":4.967278191,"remaining_time":0.09620620349},
{"learn":[62358.16887],"iteration":981,"passed_time":4.973982751,"remaining_time":0.09117279992},
{"learn":[62348.57847],"iteration":982,"passed_time":4.980609176,"remaining_time":0.08613464496},
{"learn":[62345.74664],"iteration":983,"passed_time":4.991614885,"remaining_time":0.08116446968},
{"learn":[62337.92046],"iteration":984,"passed_time":4.998522088,"remaining_time":0.07611962571},
{"learn":[62335.45729],"iteration":985,"passed_time":5.005585699,"remaining_time":0.07107322494},
{"learn":[62329.97496],"iteration":986,"passed_time":5.010531674,"remaining_time":0.06599484474},
{"learn":[62326.19857],"iteration":987,"passed_time":5.017810507,"remaining_time":0.06094506689},
{"learn":[62314.68175],"iteration":988,"passed_time":5.024038479,"remaining_time":0.05587909329},
{"learn":[62309.12092],"iteration":989,"passed_time":5.028477019,"remaining_time":0.05079269716},
{"learn":[62299.92726],"iteration":990,"passed_time":5.032410977,"remaining_time":0.04570302603},
{"learn":[62292.75284],"iteration":991,"passed_time":5.036433091,"remaining_time":0.04061639589},
{"learn":[62288.0357],"iteration":992,"passed_time":5.040731102,"remaining_time":0.0355338547},
{"learn":[62287.04493],"iteration":993,"passed_time":5.062068195,"remaining_time":0.03055574363},
{"learn":[62280.58891],"iteration":994,"passed_time":5.068384558,"remaining_time":0.02546926913},
{"learn":[62277.3052],"iteration":995,"passed_time":5.075093343,"remaining_time":0.02038190098},
{"learn":[62268.86537],"iteration":996,"passed_time":5.080585329,"remaining_time":0.01528761884},
{"learn":[62264.09934],"iteration":997,"passed_time":5.087248489,"remaining_time":0.01019488675},
{"learn":[62262.57662],"iteration":998,"passed_time":5.092729857,"remaining_time":0.005097827684},
{"learn":[62258.85138],"iteration":999,"passed_time":5.100075107,"remaining_time":0}
]}